Workbook

Sheet Reajustes
B2: PAINEL DE REAJUSTES — Base: Realizado Superlógica
B3: Edite os percentuais por categoria. Para um item específico, use a tabela debaixo.
B5: ='Previsao Anual'!E122 | D5: ='Resumo Assembleia'!D24
B6: Total Previsto | D6: Taxa Mensal (referência)
B9: REAJUSTE POR CATEGORIA
B10: Categoria | C10: Reajuste %
B11: Despesas Financeiras
B12: Despesa com Funcionários
B13: Retenções Fiscais
B14: Despesa Administrativa
B15: Manutenção
B16: Aquisição de Materiais
B17: Serviços
B18: Investimento e Equipamentos
B19: Taxas e Recolhimentos
B20: REAJUSTE POR ITEM (opcional — sobrescreve a categoria)
B21: Preencha APENAS UMA das 3 opções por item: % (col E), valor anual (col F) ou valor mensal (col G). Prioridade: mensal > anual > %. Vazio = herda o % da categoria.
B22: Item | C22: Categoria | D22: Base Anual (R$) | E22: Reajuste % do Item | F22: Valor Anual 2026 (R$) | G22: Valor Mensal 2026 (R$) | H22: % Aplicado | I22: Valor Final Anual (R$)
B23: Cotas de Capital - Sicoob | C23: Despesas Financeiras | D23: ='Previsao Anual'!C7 | H23: =IFERROR(IF(ISNUMBER(G23),(G23*12)/D23-1,IF(ISNUMBER(F23),F23/D23-1,IF(ISNUMBER(E23),E23,IF(ISNUMBER(C11),C11,0)))),0) | I23: =IF(ISNUMBER(G23),G23*12,IF(ISNUMBER(F23),F23,D23*(1+IF(ISNUMBER(E23),E23,IF(ISNUMBER(C11),C11,0)))))
B24: Reembolso | C24: Despesas Financeiras | D24: ='Previsao Anual'!C8 | H24: =IFERROR(IF(ISNUMBER(G24),(G24*12)/D24-1,IF(ISNUMBER(F24),F24/D24-1,IF(ISNUMBER(E24),E24,IF(ISNUMBER(C11),C11,0)))),0) | I24: =IF(ISNUMBER(G24),G24*12,IF(ISNUMBER(F24),F24,D24*(1+IF(ISNUMBER(E24),E24,IF(ISNUMBER(C11),C11,0)))))
B25: IRRF Poupança | C25: Despesas Financeiras | D25: ='Previsao Anual'!C9 | H25: =IFERROR(IF(ISNUMBER(G25),(G25*12)/D25-1,IF(ISNUMBER(F25),F25/D25-1,IF(ISNUMBER(E25),E25,IF(ISNUMBER(C11),C11,0)))),0) | I25: =IF(ISNUMBER(G25),G25*12,IF(ISNUMBER(F25),F25,D25*(1+IF(ISNUMBER(E25),E25,IF(ISNUMBER(C11),C11,0)))))
B26: Devolução Pagamento Reserva | C26: Despesas Financeiras | D26: ='Previsao Anual'!C10 | H26: =IFERROR(IF(ISNUMBER(G26),(G26*12)/D26-1,IF(ISNUMBER(F26),F26/D26-1,IF(ISNUMBER(E26),E26,IF(ISNUMBER(C11),C11,0)))),0) | I26: =IF(ISNUMBER(G26),G26*12,IF(ISNUMBER(F26),F26,D26*(1+IF(ISNUMBER(E26),E26,IF(ISNUMBER(C11),C11,0)))))
B27: Tarifas Bancárias - Garantidora | C27: Despesas Financeiras | D27: ='Previsao Anual'!C11 | H27: =IFERROR(IF(ISNUMBER(G27),(G27*12)/D27-1,IF(ISNUMBER(F27),F27/D27-1,IF(ISNUMBER(E27),E27,IF(ISNUMBER(C11),C11,0)))),0) | I27: =IF(ISNUMBER(G27),G27*12,IF(ISNUMBER(F27),F27,D27*(1+IF(ISNUMBER(E27),E27,IF(ISNUMBER(C11),C11,0)))))
B28: Contrato Mão de Obra Terceirizada | C28: Despesa com Funcionários | D28: ='Previsao Anual'!C15 | H28: =IFERROR(IF(ISNUMBER(G28),(G28*12)/D28-1,IF(ISNUMBER(F28),F28/D28-1,IF(ISNUMBER(E28),E28,IF(ISNUMBER(C12),C12,0)))),0) | I28: =IF(ISNUMBER(G28),G28*12,IF(ISNUMBER(F28),F28,D28*(1+IF(ISNUMBER(E28),E28,IF(ISNUMBER(C12),C12,0)))))
B29: Alimentação e Lanche | C29: Despesa com Funcionários | D29: ='Previsao Anual'!C16 | H29: =IFERROR(IF(ISNUMBER(G29),(G29*12)/D29-1,IF(ISNUMBER(F29),F29/D29-1,IF(ISNUMBER(E29),E29,IF(ISNUMBER(C12),C12,0)))),0) | I29: =IF(ISNUMBER(G29),G29*12,IF(ISNUMBER(F29),F29,D29*(1+IF(ISNUMBER(E29),E29,IF(ISNUMBER(C12),C12,0)))))
B30: Padaria | C30: Despesa com Funcionários | D30: ='Previsao Anual'!C17 | H30: =IFERROR(IF(ISNUMBER(G30),(G30*12)/D30-1,IF(ISNUMBER(F30),F30/D30-1,IF(ISNUMBER(E30),E30,IF(ISNUMBER(C12),C12,0)))),0) | I30: =IF(ISNUMBER(G30),G30*12,IF(ISNUMBER(F30),F30,D30*(1+IF(ISNUMBER(E30),E30,IF(ISNUMBER(C12),C12,0)))))
B31: ISS | C31: Retenções Fiscais | D31: ='Previsao Anual'!C21 | H31: =IFERROR(IF(ISNUMBER(G31),(G31*12)/D31-1,IF(ISNUMBER(F31),F31/D31-1,IF(ISNUMBER(E31),E31,IF(ISNUMBER(C13),C13,0)))),0) | I31: =IF(ISNUMBER(G31),G31*12,IF(ISNUMBER(F31),F31,D31*(1+IF(ISNUMBER(E31),E31,IF(ISNUMBER(C13),C13,0)))))
B32: DARF Pis Cofins CSLL | C32: Retenções Fiscais | D32: ='Previsao Anual'!C22 | H32: =IFERROR(IF(ISNUMBER(G32),(G32*12)/D32-1,IF(ISNUMBER(F32),F32/D32-1,IF(ISNUMBER(E32),E32,IF(ISNUMBER(C13),C13,0)))),0) | I32: =IF(ISNUMBER(G32),G32*12,IF(ISNUMBER(F32),F32,D32*(1+IF(ISNUMBER(E32),E32,IF(ISNUMBER(C13),C13,0)))))
B33: Honorários Administrativos | C33: Despesa Administrativa | D33: ='Previsao Anual'!C26 | H33: =IFERROR(IF(ISNUMBER(G33),(G33*12)/D33-1,IF(ISNUMBER(F33),F33/D33-1,IF(ISNUMBER(E33),E33,IF(ISNUMBER(C14),C14,0)))),0) | I33: =IF(ISNUMBER(G33),G33*12,IF(ISNUMBER(F33),F33,D33*(1+IF(ISNUMBER(E33),E33,IF(ISNUMBER(C14),C14,0)))))
B34: Honorários Síndico | C34: Despesa Administrativa | D34: ='Previsao Anual'!C27 | H34: =IFERROR(IF(ISNUMBER(G34),(G34*12)/D34-1,IF(ISNUMBER(F34),F34/D34-1,IF(ISNUMBER(E34),E34,IF(ISNUMBER(C14),C14,0)))),0) | I34: =IF(ISNUMBER(G34),G34*12,IF(ISNUMBER(F34),F34,D34*(1+IF(ISNUMBER(E34),E34,IF(ISNUMBER(C14),C14,0)))))
B35: Despesas Com Correios | C35: Despesa Administrativa | D35: ='Previsao Anual'!C28 | H35: =IFERROR(IF(ISNUMBER(G35),(G35*12)/D35-1,IF(ISNUMBER(F35),F35/D35-1,IF(ISNUMBER(E35),E35,IF(ISNUMBER(C14),C14,0)))),0) | I35: =IF(ISNUMBER(G35),G35*12,IF(ISNUMBER(F35),F35,D35*(1+IF(ISNUMBER(E35),E35,IF(ISNUMBER(C14),C14,0)))))
B36: Despesas Com Cartório | C36: Despesa Administrativa | D36: ='Previsao Anual'!C29 | H36: =IFERROR(IF(ISNUMBER(G36),(G36*12)/D36-1,IF(ISNUMBER(F36),F36/D36-1,IF(ISNUMBER(E36),E36,IF(ISNUMBER(C14),C14,0)))),0) | I36: =IF(ISNUMBER(G36),G36*12,IF(ISNUMBER(F36),F36,D36*(1+IF(ISNUMBER(E36),E36,IF(ISNUMBER(C14),C14,0)))))
B37: Despesas Com Material de Expediente | C37: Despesa Administrativa | D37: ='Previsao Anual'!C30 | H37: =IFERROR(IF(ISNUMBER(G37),(G37*12)/D37-1,IF(ISNUMBER(F37),F37/D37-1,IF(ISNUMBER(E37),E37,IF(ISNUMBER(C14),C14,0)))),0) | I37: =IF(ISNUMBER(G37),G37*12,IF(ISNUMBER(F37),F37,D37*(1+IF(ISNUMBER(E37),E37,IF(ISNUMBER(C14),C14,0)))))
B38: Honorários Advocatícios | C38: Despesa Administrativa | D38: ='Previsao Anual'!C31 | H38: =IFERROR(IF(ISNUMBER(G38),(G38*12)/D38-1,IF(ISNUMBER(F38),F38/D38-1,IF(ISNUMBER(E38),E38,IF(ISNUMBER(C14),C14,0)))),0) | I38: =IF(ISNUMBER(G38),G38*12,IF(ISNUMBER(F38),F38,D38*(1+IF(ISNUMBER(E38),E38,IF(ISNUMBER(C14),C14,0)))))
B39: Custas Processuais | C39: Despesa Administrativa | D39: ='Previsao Anual'!C32 | H39: =IFERROR(IF(ISNUMBER(G39),(G39*12)/D39-1,IF(ISNUMBER(F39),F39/D39-1,IF(ISNUMBER(E39),E39,IF(ISNUMBER(C14),C14,0)))),0) | I39: =IF(ISNUMBER(G39),G39*12,IF(ISNUMBER(F39),F39,D39*(1+IF(ISNUMBER(E39),E39,IF(ISNUMBER(C14),C14,0)))))
B40: Multa-Penalidade | C40: Despesa Administrativa | D40: ='Previsao Anual'!C33 | H40: =IFERROR(IF(ISNUMBER(G40),(G40*12)/D40-1,IF(ISNUMBER(F40),F40/D40-1,IF(ISNUMBER(E40),E40,IF(ISNUMBER(C14),C14,0)))),0) | I40: =IF(ISNUMBER(G40),G40*12,IF(ISNUMBER(F40),F40,D40*(1+IF(ISNUMBER(E40),E40,IF(ISNUMBER(C14),C14,0)))))
B41: Taxa Antecipação Garantidora | C41: Despesa Administrativa | D41: ='Previsao Anual'!C34 | H41: =IFERROR(IF(ISNUMBER(G41),(G41*12)/D41-1,IF(ISNUMBER(F41),F41/D41-1,IF(ISNUMBER(E41),E41,IF(ISNUMBER(C14),C14,0)))),0) | I41: =IF(ISNUMBER(G41),G41*12,IF(ISNUMBER(F41),F41,D41*(1+IF(ISNUMBER(E41),E41,IF(ISNUMBER(C14),C14,0)))))
B42: Despesa com Deslocamento | C42: Despesa Administrativa | D42: ='Previsao Anual'!C35 | H42: =IFERROR(IF(ISNUMBER(G42),(G42*12)/D42-1,IF(ISNUMBER(F42),F42/D42-1,IF(ISNUMBER(E42),E42,IF(ISNUMBER(C14),C14,0)))),0) | I42: =IF(ISNUMBER(G42),G42*12,IF(ISNUMBER(F42),F42,D42*(1+IF(ISNUMBER(E42),E42,IF(ISNUMBER(C14),C14,0)))))
B43: Contrato Manutenção Elevador | C43: Manutenção | D43: ='Previsao Anual'!C39 | H43: =IFERROR(IF(ISNUMBER(G43),(G43*12)/D43-1,IF(ISNUMBER(F43),F43/D43-1,IF(ISNUMBER(E43),E43,IF(ISNUMBER(C15),C15,0)))),0) | I43: =IF(ISNUMBER(G43),G43*12,IF(ISNUMBER(F43),F43,D43*(1+IF(ISNUMBER(E43),E43,IF(ISNUMBER(C15),C15,0)))))
B44: Contrato Manutenção Piscina | C44: Manutenção | D44: ='Previsao Anual'!C40 | H44: =IFERROR(IF(ISNUMBER(G44),(G44*12)/D44-1,IF(ISNUMBER(F44),F44/D44-1,IF(ISNUMBER(E44),E44,IF(ISNUMBER(C15),C15,0)))),0) | I44: =IF(ISNUMBER(G44),G44*12,IF(ISNUMBER(F44),F44,D44*(1+IF(ISNUMBER(E44),E44,IF(ISNUMBER(C15),C15,0)))))
B45: Contrato Manutenção Jardinagem | C45: Manutenção | D45: ='Previsao Anual'!C41 | H45: =IFERROR(IF(ISNUMBER(G45),(G45*12)/D45-1,IF(ISNUMBER(F45),F45/D45-1,IF(ISNUMBER(E45),E45,IF(ISNUMBER(C15),C15,0)))),0) | I45: =IF(ISNUMBER(G45),G45*12,IF(ISNUMBER(F45),F45,D45*(1+IF(ISNUMBER(E45),E45,IF(ISNUMBER(C15),C15,0)))))
B46: Contrato Manutenção Segurança Eletrônica | C46: Manutenção | D46: ='Previsao Anual'!C42 | H46: =IFERROR(IF(ISNUMBER(G46),(G46*12)/D46-1,IF(ISNUMBER(F46),F46/D46-1,IF(ISNUMBER(E46),E46,IF(ISNUMBER(C15),C15,0)))),0) | I46: =IF(ISNUMBER(G46),G46*12,IF(ISNUMBER(F46),F46,D46*(1+IF(ISNUMBER(E46),E46,IF(ISNUMBER(C15),C15,0)))))
B47: Contrato de Manutenção de Desinsetização | C47: Manutenção | D47: ='Previsao Anual'!C43 | H47: =IFERROR(IF(ISNUMBER(G47),(G47*12)/D47-1,IF(ISNUMBER(F47),F47/D47-1,IF(ISNUMBER(E47),E47,IF(ISNUMBER(C15),C15,0)))),0) | I47: =IF(ISNUMBER(G47),G47*12,IF(ISNUMBER(F47),F47,D47*(1+IF(ISNUMBER(E47),E47,IF(ISNUMBER(C15),C15,0)))))
B48: Contrato Manutenção de Segurança | C48: Manutenção | D48: ='Previsao Anual'!C44 | H48: =IFERROR(IF(ISNUMBER(G48),(G48*12)/D48-1,IF(ISNUMBER(F48),F48/D48-1,IF(ISNUMBER(E48),E48,IF(ISNUMBER(C15),C15,0)))),0) | I48: =IF(ISNUMBER(G48),G48*12,IF(ISNUMBER(F48),F48,D48*(1+IF(ISNUMBER(E48),E48,IF(ISNUMBER(C15),C15,0)))))
B49: Contrato Manutenção Bombas | C49: Manutenção | D49: ='Previsao Anual'!C45 | H49: =IFERROR(IF(ISNUMBER(G49),(G49*12)/D49-1,IF(ISNUMBER(F49),F49/D49-1,IF(ISNUMBER(E49),E49,IF(ISNUMBER(C15),C15,0)))),0) | I49: =IF(ISNUMBER(G49),G49*12,IF(ISNUMBER(F49),F49,D49*(1+IF(ISNUMBER(E49),E49,IF(ISNUMBER(C15),C15,0)))))
B50: Contrato Cx. de Gordura - Fossa e Esgoto | C50: Manutenção | D50: ='Previsao Anual'!C46 | H50: =IFERROR(IF(ISNUMBER(G50),(G50*12)/D50-1,IF(ISNUMBER(F50),F50/D50-1,IF(ISNUMBER(E50),E50,IF(ISNUMBER(C15),C15,0)))),0) | I50: =IF(ISNUMBER(G50),G50*12,IF(ISNUMBER(F50),F50,D50*(1+IF(ISNUMBER(E50),E50,IF(ISNUMBER(C15),C15,0)))))
B51: Contrato Manutenção ETE | C51: Manutenção | D51: ='Previsao Anual'!C47 | H51: =IFERROR(IF(ISNUMBER(G51),(G51*12)/D51-1,IF(ISNUMBER(F51),F51/D51-1,IF(ISNUMBER(E51),E51,IF(ISNUMBER(C15),C15,0)))),0) | I51: =IF(ISNUMBER(G51),G51*12,IF(ISNUMBER(F51),F51,D51*(1+IF(ISNUMBER(E51),E51,IF(ISNUMBER(C15),C15,0)))))
B52: Material de Limpeza | C52: Aquisição de Materiais | D52: ='Previsao Anual'!C51 | H52: =IFERROR(IF(ISNUMBER(G52),(G52*12)/D52-1,IF(ISNUMBER(F52),F52/D52-1,IF(ISNUMBER(E52),E52,IF(ISNUMBER(C16),C16,0)))),0) | I52: =IF(ISNUMBER(G52),G52*12,IF(ISNUMBER(F52),F52,D52*(1+IF(ISNUMBER(E52),E52,IF(ISNUMBER(C16),C16,0)))))
B53: Material Elétrico | C53: Aquisição de Materiais | D53: ='Previsao Anual'!C52 | H53: =IFERROR(IF(ISNUMBER(G53),(G53*12)/D53-1,IF(ISNUMBER(F53),F53/D53-1,IF(ISNUMBER(E53),E53,IF(ISNUMBER(C16),C16,0)))),0) | I53: =IF(ISNUMBER(G53),G53*12,IF(ISNUMBER(F53),F53,D53*(1+IF(ISNUMBER(E53),E53,IF(ISNUMBER(C16),C16,0)))))
B54: Material Hidráulico | C54: Aquisição de Materiais | D54: ='Previsao Anual'!C53 | H54: =IFERROR(IF(ISNUMBER(G54),(G54*12)/D54-1,IF(ISNUMBER(F54),F54/D54-1,IF(ISNUMBER(E54),E54,IF(ISNUMBER(C16),C16,0)))),0) | I54: =IF(ISNUMBER(G54),G54*12,IF(ISNUMBER(F54),F54,D54*(1+IF(ISNUMBER(E54),E54,IF(ISNUMBER(C16),C16,0)))))
B55: Material de Segurança Eletrônica | C55: Aquisição de Materiais | D55: ='Previsao Anual'!C54 | H55: =IFERROR(IF(ISNUMBER(G55),(G55*12)/D55-1,IF(ISNUMBER(F55),F55/D55-1,IF(ISNUMBER(E55),E55,IF(ISNUMBER(C16),C16,0)))),0) | I55: =IF(ISNUMBER(G55),G55*12,IF(ISNUMBER(F55),F55,D55*(1+IF(ISNUMBER(E55),E55,IF(ISNUMBER(C16),C16,0)))))
B56: Material de Pintura | C56: Aquisição de Materiais | D56: ='Previsao Anual'!C55 | H56: =IFERROR(IF(ISNUMBER(G56),(G56*12)/D56-1,IF(ISNUMBER(F56),F56/D56-1,IF(ISNUMBER(E56),E56,IF(ISNUMBER(C16),C16,0)))),0) | I56: =IF(ISNUMBER(G56),G56*12,IF(ISNUMBER(F56),F56,D56*(1+IF(ISNUMBER(E56),E56,IF(ISNUMBER(C16),C16,0)))))
B57: Material de Construção-Ferramentas | C57: Aquisição de Materiais | D57: ='Previsao Anual'!C56 | H57: =IFERROR(IF(ISNUMBER(G57),(G57*12)/D57-1,IF(ISNUMBER(F57),F57/D57-1,IF(ISNUMBER(E57),E57,IF(ISNUMBER(C16),C16,0)))),0) | I57: =IF(ISNUMBER(G57),G57*12,IF(ISNUMBER(F57),F57,D57*(1+IF(ISNUMBER(E57),E57,IF(ISNUMBER(C16),C16,0)))))
B58: Material de Uso e Consumo Condomínio | C58: Aquisição de Materiais | D58: ='Previsao Anual'!C57 | H58: =IFERROR(IF(ISNUMBER(G58),(G58*12)/D58-1,IF(ISNUMBER(F58),F58/D58-1,IF(ISNUMBER(E58),E58,IF(ISNUMBER(C16),C16,0)))),0) | I58: =IF(ISNUMBER(G58),G58*12,IF(ISNUMBER(F58),F58,D58*(1+IF(ISNUMBER(E58),E58,IF(ISNUMBER(C16),C16,0)))))
B59: Material de Confraternização-Festa | C59: Aquisição de Materiais | D59: ='Previsao Anual'!C58 | H59: =IFERROR(IF(ISNUMBER(G59),(G59*12)/D59-1,IF(ISNUMBER(F59),F59/D59-1,IF(ISNUMBER(E59),E59,IF(ISNUMBER(C16),C16,0)))),0) | I59: =IF(ISNUMBER(G59),G59*12,IF(ISNUMBER(F59),F59,D59*(1+IF(ISNUMBER(E59),E59,IF(ISNUMBER(C16),C16,0)))))
B60: Material de Informática | C60: Aquisição de Materiais | D60: ='Previsao Anual'!C59 | H60: =IFERROR(IF(ISNUMBER(G60),(G60*12)/D60-1,IF(ISNUMBER(F60),F60/D60-1,IF(ISNUMBER(E60),E60,IF(ISNUMBER(C16),C16,0)))),0) | I60: =IF(ISNUMBER(G60),G60*12,IF(ISNUMBER(F60),F60,D60*(1+IF(ISNUMBER(E60),E60,IF(ISNUMBER(C16),C16,0)))))
B61: Material de Academia | C61: Aquisição de Materiais | D61: ='Previsao Anual'!C60 | H61: =IFERROR(IF(ISNUMBER(G61),(G61*12)/D61-1,IF(ISNUMBER(F61),F61/D61-1,IF(ISNUMBER(E61),E61,IF(ISNUMBER(C16),C16,0)))),0) | I61: =IF(ISNUMBER(G61),G61*12,IF(ISNUMBER(F61),F61,D61*(1+IF(ISNUMBER(E61),E61,IF(ISNUMBER(C16),C16,0)))))
B62: Material de Piscina | C62: Aquisição de Materiais | D62: ='Previsao Anual'!C61 | H62: =IFERROR(IF(ISNUMBER(G62),(G62*12)/D62-1,IF(ISNUMBER(F62),F62/D62-1,IF(ISNUMBER(E62),E62,IF(ISNUMBER(C16),C16,0)))),0) | I62: =IF(ISNUMBER(G62),G62*12,IF(ISNUMBER(F62),F62,D62*(1+IF(ISNUMBER(E62),E62,IF(ISNUMBER(C16),C16,0)))))
B63: Material Área de Lazer | C63: Aquisição de Materiais | D63: ='Previsao Anual'!C62 | H63: =IFERROR(IF(ISNUMBER(G63),(G63*12)/D63-1,IF(ISNUMBER(F63),F63/D63-1,IF(ISNUMBER(E63),E63,IF(ISNUMBER(C16),C16,0)))),0) | I63: =IF(ISNUMBER(G63),G63*12,IF(ISNUMBER(F63),F63,D63*(1+IF(ISNUMBER(E63),E63,IF(ISNUMBER(C16),C16,0)))))
B64: Tags - Controle de Acesso | C64: Aquisição de Materiais | D64: ='Previsao Anual'!C63 | H64: =IFERROR(IF(ISNUMBER(G64),(G64*12)/D64-1,IF(ISNUMBER(F64),F64/D64-1,IF(ISNUMBER(E64),E64,IF(ISNUMBER(C16),C16,0)))),0) | I64: =IF(ISNUMBER(G64),G64*12,IF(ISNUMBER(F64),F64,D64*(1+IF(ISNUMBER(E64),E64,IF(ISNUMBER(C16),C16,0)))))
B65: Material para Portão | C65: Aquisição de Materiais | D65: ='Previsao Anual'!C64 | H65: =IFERROR(IF(ISNUMBER(G65),(G65*12)/D65-1,IF(ISNUMBER(F65),F65/D65-1,IF(ISNUMBER(E65),E65,IF(ISNUMBER(C16),C16,0)))),0) | I65: =IF(ISNUMBER(G65),G65*12,IF(ISNUMBER(F65),F65,D65*(1+IF(ISNUMBER(E65),E65,IF(ISNUMBER(C16),C16,0)))))
B66: Material de Decoração | C66: Aquisição de Materiais | D66: ='Previsao Anual'!C65 | H66: =IFERROR(IF(ISNUMBER(G66),(G66*12)/D66-1,IF(ISNUMBER(F66),F66/D66-1,IF(ISNUMBER(E66),E66,IF(ISNUMBER(C16),C16,0)))),0) | I66: =IF(ISNUMBER(G66),G66*12,IF(ISNUMBER(F66),F66,D66*(1+IF(ISNUMBER(E66),E66,IF(ISNUMBER(C16),C16,0)))))
B67: Material Salão de Festas | C67: Aquisição de Materiais | D67: ='Previsao Anual'!C66 | H67: =IFERROR(IF(ISNUMBER(G67),(G67*12)/D67-1,IF(ISNUMBER(F67),F67/D67-1,IF(ISNUMBER(E67),E67,IF(ISNUMBER(C16),C16,0)))),0) | I67: =IF(ISNUMBER(G67),G67*12,IF(ISNUMBER(F67),F67,D67*(1+IF(ISNUMBER(E67),E67,IF(ISNUMBER(C16),C16,0)))))
B68: Material de Interfone | C68: Aquisição de Materiais | D68: ='Previsao Anual'!C67 | H68: =IFERROR(IF(ISNUMBER(G68),(G68*12)/D68-1,IF(ISNUMBER(F68),F68/D68-1,IF(ISNUMBER(E68),E68,IF(ISNUMBER(C16),C16,0)))),0) | I68: =IF(ISNUMBER(G68),G68*12,IF(ISNUMBER(F68),F68,D68*(1+IF(ISNUMBER(E68),E68,IF(ISNUMBER(C16),C16,0)))))
B69: Ferramentas-materiais para manutenção | C69: Aquisição de Materiais | D69: ='Previsao Anual'!C68 | H69: =IFERROR(IF(ISNUMBER(G69),(G69*12)/D69-1,IF(ISNUMBER(F69),F69/D69-1,IF(ISNUMBER(E69),E69,IF(ISNUMBER(C16),C16,0)))),0) | I69: =IF(ISNUMBER(G69),G69*12,IF(ISNUMBER(F69),F69,D69*(1+IF(ISNUMBER(E69),E69,IF(ISNUMBER(C16),C16,0)))))
B70: Material de Sinalização | C70: Aquisição de Materiais | D70: ='Previsao Anual'!C69 | H70: =IFERROR(IF(ISNUMBER(G70),(G70*12)/D70-1,IF(ISNUMBER(F70),F70/D70-1,IF(ISNUMBER(E70),E70,IF(ISNUMBER(C16),C16,0)))),0) | I70: =IF(ISNUMBER(G70),G70*12,IF(ISNUMBER(F70),F70,D70*(1+IF(ISNUMBER(E70),E70,IF(ISNUMBER(C16),C16,0)))))
B71: Material de Extintor | C71: Aquisição de Materiais | D71: ='Previsao Anual'!C70 | H71: =IFERROR(IF(ISNUMBER(G71),(G71*12)/D71-1,IF(ISNUMBER(F71),F71/D71-1,IF(ISNUMBER(E71),E71,IF(ISNUMBER(C16),C16,0)))),0) | I71: =IF(ISNUMBER(G71),G71*12,IF(ISNUMBER(F71),F71,D71*(1+IF(ISNUMBER(E71),E71,IF(ISNUMBER(C16),C16,0)))))
B72: Seguro Condominial | C72: Serviços | D72: ='Previsao Anual'!C74 | H72: =IFERROR(IF(ISNUMBER(G72),(G72*12)/D72-1,IF(ISNUMBER(F72),F72/D72-1,IF(ISNUMBER(E72),E72,IF(ISNUMBER(C17),C17,0)))),0) | I72: =IF(ISNUMBER(G72),G72*12,IF(ISNUMBER(F72),F72,D72*(1+IF(ISNUMBER(E72),E72,IF(ISNUMBER(C17),C17,0)))))
B73: Serviço de Pintura | C73: Serviços | D73: ='Previsao Anual'!C75 | H73: =IFERROR(IF(ISNUMBER(G73),(G73*12)/D73-1,IF(ISNUMBER(F73),F73/D73-1,IF(ISNUMBER(E73),E73,IF(ISNUMBER(C17),C17,0)))),0) | I73: =IF(ISNUMBER(G73),G73*12,IF(ISNUMBER(F73),F73,D73*(1+IF(ISNUMBER(E73),E73,IF(ISNUMBER(C17),C17,0)))))
B74: Serviço Elétrico | C74: Serviços | D74: ='Previsao Anual'!C76 | H74: =IFERROR(IF(ISNUMBER(G74),(G74*12)/D74-1,IF(ISNUMBER(F74),F74/D74-1,IF(ISNUMBER(E74),E74,IF(ISNUMBER(C17),C17,0)))),0) | I74: =IF(ISNUMBER(G74),G74*12,IF(ISNUMBER(F74),F74,D74*(1+IF(ISNUMBER(E74),E74,IF(ISNUMBER(C17),C17,0)))))
B75: Serviço de Engenharia | C75: Serviços | D75: ='Previsao Anual'!C77 | H75: =IFERROR(IF(ISNUMBER(G75),(G75*12)/D75-1,IF(ISNUMBER(F75),F75/D75-1,IF(ISNUMBER(E75),E75,IF(ISNUMBER(C17),C17,0)))),0) | I75: =IF(ISNUMBER(G75),G75*12,IF(ISNUMBER(F75),F75,D75*(1+IF(ISNUMBER(E75),E75,IF(ISNUMBER(C17),C17,0)))))
B76: Serviço de Desinsetização | C76: Serviços | D76: ='Previsao Anual'!C78 | H76: =IFERROR(IF(ISNUMBER(G76),(G76*12)/D76-1,IF(ISNUMBER(F76),F76/D76-1,IF(ISNUMBER(E76),E76,IF(ISNUMBER(C17),C17,0)))),0) | I76: =IF(ISNUMBER(G76),G76*12,IF(ISNUMBER(F76),F76,D76*(1+IF(ISNUMBER(E76),E76,IF(ISNUMBER(C17),C17,0)))))
B77: Serviço Gráficos | C77: Serviços | D77: ='Previsao Anual'!C79 | H77: =IFERROR(IF(ISNUMBER(G77),(G77*12)/D77-1,IF(ISNUMBER(F77),F77/D77-1,IF(ISNUMBER(E77),E77,IF(ISNUMBER(C17),C17,0)))),0) | I77: =IF(ISNUMBER(G77),G77*12,IF(ISNUMBER(F77),F77,D77*(1+IF(ISNUMBER(E77),E77,IF(ISNUMBER(C17),C17,0)))))
B78: Serviço de Locação | C78: Serviços | D78: ='Previsao Anual'!C80 | H78: =IFERROR(IF(ISNUMBER(G78),(G78*12)/D78-1,IF(ISNUMBER(F78),F78/D78-1,IF(ISNUMBER(E78),E78,IF(ISNUMBER(C17),C17,0)))),0) | I78: =IF(ISNUMBER(G78),G78*12,IF(ISNUMBER(F78),F78,D78*(1+IF(ISNUMBER(E78),E78,IF(ISNUMBER(C17),C17,0)))))
B79: Serviço de Chaveiro | C79: Serviços | D79: ='Previsao Anual'!C81 | H79: =IFERROR(IF(ISNUMBER(G79),(G79*12)/D79-1,IF(ISNUMBER(F79),F79/D79-1,IF(ISNUMBER(E79),E79,IF(ISNUMBER(C17),C17,0)))),0) | I79: =IF(ISNUMBER(G79),G79*12,IF(ISNUMBER(F79),F79,D79*(1+IF(ISNUMBER(E79),E79,IF(ISNUMBER(C17),C17,0)))))
B80: Serviço de Serralheria | C80: Serviços | D80: ='Previsao Anual'!C82 | H80: =IFERROR(IF(ISNUMBER(G80),(G80*12)/D80-1,IF(ISNUMBER(F80),F80/D80-1,IF(ISNUMBER(E80),E80,IF(ISNUMBER(C17),C17,0)))),0) | I80: =IF(ISNUMBER(G80),G80*12,IF(ISNUMBER(F80),F80,D80*(1+IF(ISNUMBER(E80),E80,IF(ISNUMBER(C17),C17,0)))))
B81: Serviço Hidráulico | C81: Serviços | D81: ='Previsao Anual'!C83 | H81: =IFERROR(IF(ISNUMBER(G81),(G81*12)/D81-1,IF(ISNUMBER(F81),F81/D81-1,IF(ISNUMBER(E81),E81,IF(ISNUMBER(C17),C17,0)))),0) | I81: =IF(ISNUMBER(G81),G81*12,IF(ISNUMBER(F81),F81,D81*(1+IF(ISNUMBER(E81),E81,IF(ISNUMBER(C17),C17,0)))))
B82: Serviço de Informática- Internet | C82: Serviços | D82: ='Previsao Anual'!C84 | H82: =IFERROR(IF(ISNUMBER(G82),(G82*12)/D82-1,IF(ISNUMBER(F82),F82/D82-1,IF(ISNUMBER(E82),E82,IF(ISNUMBER(C17),C17,0)))),0) | I82: =IF(ISNUMBER(G82),G82*12,IF(ISNUMBER(F82),F82,D82*(1+IF(ISNUMBER(E82),E82,IF(ISNUMBER(C17),C17,0)))))
B83: Serviço em Portão | C83: Serviços | D83: ='Previsao Anual'!C85 | H83: =IFERROR(IF(ISNUMBER(G83),(G83*12)/D83-1,IF(ISNUMBER(F83),F83/D83-1,IF(ISNUMBER(E83),E83,IF(ISNUMBER(C17),C17,0)))),0) | I83: =IF(ISNUMBER(G83),G83*12,IF(ISNUMBER(F83),F83,D83*(1+IF(ISNUMBER(E83),E83,IF(ISNUMBER(C17),C17,0)))))
B84: Serviço de Jardinagem | C84: Serviços | D84: ='Previsao Anual'!C86 | H84: =IFERROR(IF(ISNUMBER(G84),(G84*12)/D84-1,IF(ISNUMBER(F84),F84/D84-1,IF(ISNUMBER(E84),E84,IF(ISNUMBER(C17),C17,0)))),0) | I84: =IF(ISNUMBER(G84),G84*12,IF(ISNUMBER(F84),F84,D84*(1+IF(ISNUMBER(E84),E84,IF(ISNUMBER(C17),C17,0)))))
B85: Serviço de Reparo | C85: Serviços | D85: ='Previsao Anual'!C87 | H85: =IFERROR(IF(ISNUMBER(G85),(G85*12)/D85-1,IF(ISNUMBER(F85),F85/D85-1,IF(ISNUMBER(E85),E85,IF(ISNUMBER(C17),C17,0)))),0) | I85: =IF(ISNUMBER(G85),G85*12,IF(ISNUMBER(F85),F85,D85*(1+IF(ISNUMBER(E85),E85,IF(ISNUMBER(C17),C17,0)))))
B86: Serviço de Marcenária | C86: Serviços | D86: ='Previsao Anual'!C88 | H86: =IFERROR(IF(ISNUMBER(G86),(G86*12)/D86-1,IF(ISNUMBER(F86),F86/D86-1,IF(ISNUMBER(E86),E86,IF(ISNUMBER(C17),C17,0)))),0) | I86: =IF(ISNUMBER(G86),G86*12,IF(ISNUMBER(F86),F86,D86*(1+IF(ISNUMBER(E86),E86,IF(ISNUMBER(C17),C17,0)))))
B87: Serviço de Descupinização | C87: Serviços | D87: ='Previsao Anual'!C89 | H87: =IFERROR(IF(ISNUMBER(G87),(G87*12)/D87-1,IF(ISNUMBER(F87),F87/D87-1,IF(ISNUMBER(E87),E87,IF(ISNUMBER(C17),C17,0)))),0) | I87: =IF(ISNUMBER(G87),G87*12,IF(ISNUMBER(F87),F87,D87*(1+IF(ISNUMBER(E87),E87,IF(ISNUMBER(C17),C17,0)))))
B88: Serviço Manutenção | C88: Serviços | D88: ='Previsao Anual'!C90 | H88: =IFERROR(IF(ISNUMBER(G88),(G88*12)/D88-1,IF(ISNUMBER(F88),F88/D88-1,IF(ISNUMBER(E88),E88,IF(ISNUMBER(C17),C17,0)))),0) | I88: =IF(ISNUMBER(G88),G88*12,IF(ISNUMBER(F88),F88,D88*(1+IF(ISNUMBER(E88),E88,IF(ISNUMBER(C17),C17,0)))))
B89: Serviço na Área de Lazer | C89: Serviços | D89: ='Previsao Anual'!C91 | H89: =IFERROR(IF(ISNUMBER(G89),(G89*12)/D89-1,IF(ISNUMBER(F89),F89/D89-1,IF(ISNUMBER(E89),E89,IF(ISNUMBER(C17),C17,0)))),0) | I89: =IF(ISNUMBER(G89),G89*12,IF(ISNUMBER(F89),F89,D89*(1+IF(ISNUMBER(E89),E89,IF(ISNUMBER(C17),C17,0)))))
B90: Obras-Melhorias | C90: Serviços | D90: ='Previsao Anual'!C92 | H90: =IFERROR(IF(ISNUMBER(G90),(G90*12)/D90-1,IF(ISNUMBER(F90),F90/D90-1,IF(ISNUMBER(E90),E90,IF(ISNUMBER(C17),C17,0)))),0) | I90: =IF(ISNUMBER(G90),G90*12,IF(ISNUMBER(F90),F90,D90*(1+IF(ISNUMBER(E90),E90,IF(ISNUMBER(C17),C17,0)))))
B91: Serviço Segurança Eletrônica | C91: Serviços | D91: ='Previsao Anual'!C93 | H91: =IFERROR(IF(ISNUMBER(G91),(G91*12)/D91-1,IF(ISNUMBER(F91),F91/D91-1,IF(ISNUMBER(E91),E91,IF(ISNUMBER(C17),C17,0)))),0) | I91: =IF(ISNUMBER(G91),G91*12,IF(ISNUMBER(F91),F91,D91*(1+IF(ISNUMBER(E91),E91,IF(ISNUMBER(C17),C17,0)))))
B92: Serviço de Reparo na bomba | C92: Serviços | D92: ='Previsao Anual'!C94 | H92: =IFERROR(IF(ISNUMBER(G92),(G92*12)/D92-1,IF(ISNUMBER(F92),F92/D92-1,IF(ISNUMBER(E92),E92,IF(ISNUMBER(C17),C17,0)))),0) | I92: =IF(ISNUMBER(G92),G92*12,IF(ISNUMBER(F92),F92,D92*(1+IF(ISNUMBER(E92),E92,IF(ISNUMBER(C17),C17,0)))))
B93: Serviço de Vistoria | C93: Serviços | D93: ='Previsao Anual'!C95 | H93: =IFERROR(IF(ISNUMBER(G93),(G93*12)/D93-1,IF(ISNUMBER(F93),F93/D93-1,IF(ISNUMBER(E93),E93,IF(ISNUMBER(C17),C17,0)))),0) | I93: =IF(ISNUMBER(G93),G93*12,IF(ISNUMBER(F93),F93,D93*(1+IF(ISNUMBER(E93),E93,IF(ISNUMBER(C17),C17,0)))))
B94: Serviço de Reparo de Elevador | C94: Serviços | D94: ='Previsao Anual'!C96 | H94: =IFERROR(IF(ISNUMBER(G94),(G94*12)/D94-1,IF(ISNUMBER(F94),F94/D94-1,IF(ISNUMBER(E94),E94,IF(ISNUMBER(C17),C17,0)))),0) | I94: =IF(ISNUMBER(G94),G94*12,IF(ISNUMBER(F94),F94,D94*(1+IF(ISNUMBER(E94),E94,IF(ISNUMBER(C17),C17,0)))))
B95: Serviço de Manutenção Extintores | C95: Serviços | D95: ='Previsao Anual'!C97 | H95: =IFERROR(IF(ISNUMBER(G95),(G95*12)/D95-1,IF(ISNUMBER(F95),F95/D95-1,IF(ISNUMBER(E95),E95,IF(ISNUMBER(C17),C17,0)))),0) | I95: =IF(ISNUMBER(G95),G95*12,IF(ISNUMBER(F95),F95,D95*(1+IF(ISNUMBER(E95),E95,IF(ISNUMBER(C17),C17,0)))))
B96: Serviço Prestados | C96: Serviços | D96: ='Previsao Anual'!C98 | H96: =IFERROR(IF(ISNUMBER(G96),(G96*12)/D96-1,IF(ISNUMBER(F96),F96/D96-1,IF(ISNUMBER(E96),E96,IF(ISNUMBER(C17),C17,0)))),0) | I96: =IF(ISNUMBER(G96),G96*12,IF(ISNUMBER(F96),F96,D96*(1+IF(ISNUMBER(E96),E96,IF(ISNUMBER(C17),C17,0)))))
B97: Serviço de Comunicação Visual | C97: Serviços | D97: ='Previsao Anual'!C99 | H97: =IFERROR(IF(ISNUMBER(G97),(G97*12)/D97-1,IF(ISNUMBER(F97),F97/D97-1,IF(ISNUMBER(E97),E97,IF(ISNUMBER(C17),C17,0)))),0) | I97: =IF(ISNUMBER(G97),G97*12,IF(ISNUMBER(F97),F97,D97*(1+IF(ISNUMBER(E97),E97,IF(ISNUMBER(C17),C17,0)))))
B98: Serviço de Ar Condicionado | C98: Serviços | D98: ='Previsao Anual'!C100 | H98: =IFERROR(IF(ISNUMBER(G98),(G98*12)/D98-1,IF(ISNUMBER(F98),F98/D98-1,IF(ISNUMBER(E98),E98,IF(ISNUMBER(C17),C17,0)))),0) | I98: =IF(ISNUMBER(G98),G98*12,IF(ISNUMBER(F98),F98,D98*(1+IF(ISNUMBER(E98),E98,IF(ISNUMBER(C17),C17,0)))))
B99: Serviço de Frete | C99: Serviços | D99: ='Previsao Anual'!C101 | H99: =IFERROR(IF(ISNUMBER(G99),(G99*12)/D99-1,IF(ISNUMBER(F99),F99/D99-1,IF(ISNUMBER(E99),E99,IF(ISNUMBER(C17),C17,0)))),0) | I99: =IF(ISNUMBER(G99),G99*12,IF(ISNUMBER(F99),F99,D99*(1+IF(ISNUMBER(E99),E99,IF(ISNUMBER(C17),C17,0)))))
B100: Serviço de Reforma Móveis e Utensílios | C100: Serviços | D100: ='Previsao Anual'!C102 | H100: =IFERROR(IF(ISNUMBER(G100),(G100*12)/D100-1,IF(ISNUMBER(F100),F100/D100-1,IF(ISNUMBER(E100),E100,IF(ISNUMBER(C17),C17,0)))),0) | I100: =IF(ISNUMBER(G100),G100*12,IF(ISNUMBER(F100),F100,D100*(1+IF(ISNUMBER(E100),E100,IF(ISNUMBER(C17),C17,0)))))
B101: Serviço em Aparelho de Academia | C101: Serviços | D101: ='Previsao Anual'!C103 | H101: =IFERROR(IF(ISNUMBER(G101),(G101*12)/D101-1,IF(ISNUMBER(F101),F101/D101-1,IF(ISNUMBER(E101),E101,IF(ISNUMBER(C17),C17,0)))),0) | I101: =IF(ISNUMBER(G101),G101*12,IF(ISNUMBER(F101),F101,D101*(1+IF(ISNUMBER(E101),E101,IF(ISNUMBER(C17),C17,0)))))
B102: Serviço Manutenção de Caixa d água | C102: Serviços | D102: ='Previsao Anual'!C104 | H102: =IFERROR(IF(ISNUMBER(G102),(G102*12)/D102-1,IF(ISNUMBER(F102),F102/D102-1,IF(ISNUMBER(E102),E102,IF(ISNUMBER(C17),C17,0)))),0) | I102: =IF(ISNUMBER(G102),G102*12,IF(ISNUMBER(F102),F102,D102*(1+IF(ISNUMBER(E102),E102,IF(ISNUMBER(C17),C17,0)))))
B103: Serviço Eletrônico Obra | C103: Serviços | D103: ='Previsao Anual'!C105 | H103: =IFERROR(IF(ISNUMBER(G103),(G103*12)/D103-1,IF(ISNUMBER(F103),F103/D103-1,IF(ISNUMBER(E103),E103,IF(ISNUMBER(C17),C17,0)))),0) | I103: =IF(ISNUMBER(G103),G103*12,IF(ISNUMBER(F103),F103,D103*(1+IF(ISNUMBER(E103),E103,IF(ISNUMBER(C17),C17,0)))))
B104: Serviços - Obra Fachada | C104: Serviços | D104: ='Previsao Anual'!C106 | H104: =IFERROR(IF(ISNUMBER(G104),(G104*12)/D104-1,IF(ISNUMBER(F104),F104/D104-1,IF(ISNUMBER(E104),E104,IF(ISNUMBER(C17),C17,0)))),0) | I104: =IF(ISNUMBER(G104),G104*12,IF(ISNUMBER(F104),F104,D104*(1+IF(ISNUMBER(E104),E104,IF(ISNUMBER(C17),C17,0)))))
...

Sheet Previsao Anual
B2: PREVISÃO ANUAL 2026
B3: Os percentuais vêm da aba 'Reajustes'. Não edite nada aqui — só visualize.
B5: Item | C5: Base Anual (R$) | D5: Reajuste % | E5: Previsão 2026 (R$) | F5: Mensal (R$)
B6: Despesas Financeiras
B7: Cotas de Capital - Sicoob | C7: 60 | D7: =Reajustes!H23 | E7: =Reajustes!I23 | F7: =E7/12
B8: Reembolso | C8: 193.15 | D8: =Reajustes!H24 | E8: =Reajustes!I24 | F8: =E8/12
B9: IRRF Poupança | C9: 5577.22 | D9: =Reajustes!H25 | E9: =Reajustes!I25 | F9: =E9/12
B10: Devolução Pagamento Reserva | C10: 279.49 | D10: =Reajustes!H26 | E10: =Reajustes!I26 | F10: =E10/12
B11: Tarifas Bancárias - Garantidora | C11: 7260 | D11: =Reajustes!H27 | E11: =Reajustes!I27 | F11: =E11/12
B12: Total Despesas Financeiras | C12: =SUM(C7:C11) | E12: =SUM(E7:E11) | F12: =E12/12
B14: Despesa com Funcionários
B15: Contrato Mão de Obra Terceirizada | C15: 590090.19 | D15: =Reajustes!H28 | E15: =Reajustes!I28 | F15: =E15/12
B16: Alimentação e Lanche | C16: 2298.02 | D16: =Reajustes!H29 | E16: =Reajustes!I29 | F16: =E16/12
B17: Padaria | C17: 1755.44 | D17: =Reajustes!H30 | E17: =Reajustes!I30 | F17: =E17/12
B18: Total Despesa com Funcionários | C18: =SUM(C15:C17) | E18: =SUM(E15:E17) | F18: =E18/12
B20: Retenções Fiscais
B21: ISS | C21: 45080.18 | D21: =Reajustes!H31 | E21: =Reajustes!I31 | F21: =E21/12
B22: DARF Pis Cofins CSLL | C22: 93567.39 | D22: =Reajustes!H32 | E22: =Reajustes!I32 | F22: =E22/12
B23: Total Retenções Fiscais | C23: =SUM(C21:C22) | E23: =SUM(E21:E22) | F23: =E23/12
B25: Despesa Administrativa
B26: Honorários Administrativos | C26: 22442 | D26: =Reajustes!H33 | E26: =Reajustes!I33 | F26: =E26/12
B27: Honorários Síndico | C27: 38400 | D27: =Reajustes!H34 | E27: =Reajustes!I34 | F27: =E27/12
B28: Despesas Com Correios | C28: 133 | D28: =Reajustes!H35 | E28: =Reajustes!I35 | F28: =E28/12
B29: Despesas Com Cartório | C29: 718.72 | D29: =Reajustes!H36 | E29: =Reajustes!I36 | F29: =E29/12
B30: Despesas Com Material de Expediente | C30: 734.92 | D30: =Reajustes!H37 | E30: =Reajustes!I37 | F30: =E30/12
B31: Honorários Advocatícios | C31: 15939 | D31: =Reajustes!H38 | E31: =Reajustes!I38 | F31: =E31/12
B32: Custas Processuais | C32: 1013.32 | D32: =Reajustes!H39 | E32: =Reajustes!I39 | F32: =E32/12
B33: Multa-Penalidade | C33: 22.3 | D33: =Reajustes!H40 | E33: =Reajustes!I40 | F33: =E33/12
B34: Taxa Antecipação Garantidora | C34: 38918.44 | D34: =Reajustes!H41 | E34: =Reajustes!I41 | F34: =E34/12
B35: Despesa com Deslocamento | C35: 30.63 | D35: =Reajustes!H42 | E35: =Reajustes!I42 | F35: =E35/12
B36: Total Despesa Administrativa | C36: =SUM(C26:C35) | E36: =SUM(E26:E35) | F36: =E36/12
B38: Manutenção
B39: Contrato Manutenção Elevador | C39: 17433.48 | D39: =Reajustes!H43 | E39: =Reajustes!I43 | F39: =E39/12
B40: Contrato Manutenção Piscina | C40: 18084 | D40: =Reajustes!H44 | E40: =Reajustes!I44 | F40: =E40/12
B41: Contrato Manutenção Jardinagem | C41: 9775 | D41: =Reajustes!H45 | E41: =Reajustes!I45 | F41: =E41/12
B42: Contrato Manutenção Segurança Eletrônica | C42: 15416.46 | D42: =Reajustes!H46 | E42: =Reajustes!I46 | F42: =E42/12
B43: Contrato de Manutenção de Desinsetização | C43: 6633.73 | D43: =Reajustes!H47 | E43: =Reajustes!I47 | F43: =E43/12
B44: Contrato Manutenção de Segurança | C44: 819.28 | D44: =Reajustes!H48 | E44: =Reajustes!I48 | F44: =E44/12
B45: Contrato Manutenção Bombas | C45: 3430.94 | D45: =Reajustes!H49 | E45: =Reajustes!I49 | F45: =E45/12
B46: Contrato Cx. de Gordura - Fossa e Esgoto | C46: 13159.4 | D46: =Reajustes!H50 | E46: =Reajustes!I50 | F46: =E46/12
B47: Contrato Manutenção ETE | C47: 967.6 | D47: =Reajustes!H51 | E47: =Reajustes!I51 | F47: =E47/12
B48: Total Manutenção | C48: =SUM(C39:C47) | E48: =SUM(E39:E47) | F48: =E48/12
B50: Aquisição de Materiais
B51: Material de Limpeza | C51: 18989.81 | D51: =Reajustes!H52 | E51: =Reajustes!I52 | F51: =E51/12
B52: Material Elétrico | C52: 5115.51 | D52: =Reajustes!H53 | E52: =Reajustes!I53 | F52: =E52/12
B53: Material Hidráulico | C53: 96.89 | D53: =Reajustes!H54 | E53: =Reajustes!I54 | F53: =E53/12
B54: Material de Segurança Eletrônica | C54: 15613.33 | D54: =Reajustes!H55 | E54: =Reajustes!I55 | F54: =E54/12
B55: Material de Pintura | C55: 6309 | D55: =Reajustes!H56 | E55: =Reajustes!I56 | F55: =E55/12
B56: Material de Construção-Ferramentas | C56: 8122.73 | D56: =Reajustes!H57 | E56: =Reajustes!I57 | F56: =E56/12
B57: Material de Uso e Consumo Condomínio | C57: 4827.64 | D57: =Reajustes!H58 | E57: =Reajustes!I58 | F57: =E57/12
B58: Material de Confraternização-Festa | C58: 2885.24 | D58: =Reajustes!H59 | E58: =Reajustes!I59 | F58: =E58/12
B59: Material de Informática | C59: 1064.89 | D59: =Reajustes!H60 | E59: =Reajustes!I60 | F59: =E59/12
B60: Material de Academia | C60: 10453.97 | D60: =Reajustes!H61 | E60: =Reajustes!I61 | F60: =E60/12
B61: Material de Piscina | C61: 390.77 | D61: =Reajustes!H62 | E61: =Reajustes!I62 | F61: =E61/12
B62: Material Área de Lazer | C62: 7414 | D62: =Reajustes!H63 | E62: =Reajustes!I63 | F62: =E62/12
... B70: Material de Extintor | C70: 3219 | D70: =Reajustes!H71 | E70: =Reajustes!I71 | F70: =E70/12
B71: Total Aquisição de Materiais | C71: =SUM(C51:C70) | E71: =SUM(E51:E70) | F71: =E71/12
B73: Serviços
B74: Seguro Condominial | C74: 6602.19 | D74: =Reajustes!H72 | E74: =Reajustes!I72 | F74: =E74/12
B75: Serviço de Pintura | C75: 500 | D75: =Reajustes!H73 | E75: =Reajustes!I73 | F75: =E75/12
B76: Serviço Elétrico | C76: 2313.25 | D76: =Reajustes!H74 | E76: =Reajustes!I74 | F76: =E76/12
B77: Serviço de Engenharia | C77: 10373.1 | D77: =Reajustes!H75 | E77: =Reajustes!I75 | F77: =E77/12
B78: Serviço de Desinsetização | C78: 285 | D78: =Reajustes!H76 | E78: =Reajustes!I76 | F78: =E78/12
B79: Serviço Gráficos | C79: 247 | D79: =Reajustes!H77 | E79: =Reajustes!I77 | F79: =E79/12
B80: Serviço de Locação | C80: 1670.44 | D80: =Reajustes!H78 | E80: =Reajustes!I78 | F80: =E80/12
B81: Serviço de Chaveiro | C81: 130 | D81: =Reajustes!H79 | E81: =Reajustes!I79 | F81: =E81/12
B82: Serviço de Serralheria | C82: 13917 | D82: =Reajustes!H80 | E82: =Reajustes!I80 | F82: =E82/12
B83: Serviço Hidráulico | C83: 7100 | D83: =Reajustes!H81 | E83: =Reajustes!I81 | F83: =E83/12
B84: Serviço de Informática- Internet | C84: 418 | D84: =Reajustes!H82 | E84: =Reajustes!I82 | F84: =E84/12
B85: Serviço em Portão | C85: 1418.15 | D85: =Reajustes!H83 | E85: =Reajustes!I83 | F85: =E85/12
... B107: Serviços - Obra Telhado | C107: 2100 | D107: =Reajustes!H105 | E107: =Reajustes!I105 | F107: =E107/12
B108: Total Serviços | C108: =SUM(C74:C107) | E108: =SUM(E74:E107) | F108: =E108/12
B110: Investimento e Equipamentos
B111: Móveis e Utensílios | C111: 3212.34 | D111: =Reajustes!H106 | E111: =Reajustes!I106 | F111: =E111/12
B112: Informática | C112: 740 | D112: =Reajustes!H107 | E112: =Reajustes!I107 | F112: =E112/12
B113: Eletrodoméstico-Eletroeletrônico | C113: 2543.7 | D113: =Reajustes!H108 | E113: =Reajustes!I108 | F113: =E113/12
B114: Máquinas-Equipamentos | C114: 3449.98 | D114: =Reajustes!H109 | E114: =Reajustes!I109 | F114: =E114/12
B115: Container de Lixo | C115: 1860 | D115: =Reajustes!H110 | E115: =Reajustes!I110 | F115: =E115/12
B116: Total Investimento e Equipamentos | C116: =SUM(C111:C115) | E116: =SUM(E111:E115) | F116: =E116/12
B118: Taxas e Recolhimentos
B119: ART - Taxa Conselho Regional Engenharia | C119: 271.47 | D119: =Reajustes!H111 | E119: =Reajustes!I111 | F119: =E119/12
B120: Total Taxas e Recolhimentos | C120: =SUM(C119:C119) | E120: =SUM(E119:E119) | F120: =E120/12
B122: TOTAL GERAL DE DESPESAS | C122: =C12+C18+C23+C36+C48+C71+C108+C116+C120 | E122: =E12+E18+E23+E36+E48+E71+E108+E116+E120 | F122: =E122/12

Sheet Previsao Mensal
B2: PREVISÃO MENSAL 2026
B3: Valores mensais já com reajuste aplicado. Os percentuais vêm da aba 'Reajustes'.
B5: Item | C5: Jan/26 | D5: Fev/26 | E5: Mar/26 | F5: Abr/26 | G5: Mai/26 | H5: Jun/26 | I5: Jul/26 | J5: Ago/26 | K5: Set/26 | L5: Out/26 | M5: Nov/26 | N5: Dez/26 | O5: Total Anual
B6: Despesas Financeiras
B7: Cotas de Capital - Sicoob | C7: =0.0*(1+Reajustes!H23) | D7: =0.0*(1+Reajustes!H23) | E7: =0.0*(1+Reajustes!H23) | F7: =0.0*(1+Reajustes!H23) | G7: =0.0*(1+Reajustes!H23) | H7: =0.0*(1+Reajustes!H23) | I7: =0.0*(1+Reajustes!H23) | J7: =0.0*(1+Reajustes!H23) | K7: =0.0*(1+Reajustes!H23) | L7: =0.0*(1+Reajustes!H23) | M7: =0.0*(1+Reajustes!H23) | N7: =60.0*(1+Reajustes!H23) | O7: =SUM(C7:N7)
B8: Reembolso | C8: =0.0*(1+Reajustes!H24) | D8: =0.0*(1+Reajustes!H24) | E8: =62.11*(1+Reajustes!H24) | F8: =0.0*(1+Reajustes!H24) | G8: =31.05*(1+Reajustes!H24) | H8: =0.0*(1+Reajustes!H24) | I8: =0.0*(1+Reajustes!H24) | J8: =99.99*(1+Reajustes!H24) | K8: =0.0*(1+Reajustes!H24) | L8: =0.0*(1+Reajustes!H24) | M8: =0.0*(1+Reajustes!H24) | N8: =0.0*(1+Reajustes!H24) | O8: =SUM(C8:N8)
B9: IRRF Poupança | C9: =528.32*(1+Reajustes!H25) | D9: =579.8*(1+Reajustes!H25) | E9: =645.55*(1+Reajustes!H25) | F9: =692.6*(1+Reajustes!H25) | G9: =732.26*(1+Reajustes!H25) | H9: =787.2*(1+Reajustes!H25) | I9: =0.0*(1+Reajustes!H25) | J9: =558.95*(1+Reajustes!H25) | K9: =344.95*(1+Reajustes!H25) | L9: =339.15*(1+Reajustes!H25) | M9: =368.44*(1+Reajustes!H25) | N9: =0.0*(1+Reajustes!H25) | O9: =SUM(C9:N9)
B10: Devolução Pagamento Reserva | C10: =0.0*(1+Reajustes!H26) | D10: =0.0*(1+Reajustes!H26) | E10: =62.11*(1+Reajustes!H26) | F10: =62.11*(1+Reajustes!H26) | G10: =0.0*(1+Reajustes!H26) | H10: =31.05*(1+Reajustes!H26) | I10: =0.0*(1+Reajustes!H26) | J10: =0.0*(1+Reajustes!H26) | K10: =62.11*(1+Reajustes!H26) | L10: =0.0*(1+Reajustes!H26) | M10: =62.11*(1+Reajustes!H26) | N10: =0.0*(1+Reajustes!H26) | O10: =SUM(C10:N10)
B11: Tarifas Bancárias - Garantidora | C11: =660.0*(1+Reajustes!H27) | D11: =660.0*(1+Reajustes!H27) | E11: =660.0*(1+Reajustes!H27) | F11: =660.0*(1+Reajustes!H27) | G11: =660.0*(1+Reajustes!H27) | H11: =660.0*(1+Reajustes!H27) | I11: =660.0*(1+Reajustes!H27) | J11: =660.0*(1+Reajustes!H27) | K11: =660.0*(1+Reajustes!H27) | L11: =660.0*(1+Reajustes!H27) | M11: =660.0*(1+Reajustes!H27) | N11: =0.0*(1+Reajustes!H27) | O11: =SUM(C11:N11)
B12: Total Despesas Financeiras | C12: =SUM(C7:C11) | D12: =SUM(D7:D11) | E12: =SUM(E7:E11) | F12: =SUM(F7:F11) | G12: =SUM(G7:G11) | H12: =SUM(H7:H11) | I12: =SUM(I7:I11) | J12: =SUM(J7:J11) | ... O12: =SUM(O7:O11)
B14: Despesa com Funcionários
B15: Contrato Mão de Obra Terceirizada | C15: =55556.6*(1+Reajustes!H28) | D15: =57451.76*(1+Reajustes!H28) | E15: =57451.76*(1+Reajustes!H28) | F15: =57451.76*(1+Reajustes!H28) | G15: =36676.66*(1+Reajustes!H28) | H15: =0.0*(1+Reajustes!H28) | I15: =126672.42*(1+Reajustes!H28) | J15: =58223.72*(1+Reajustes!H28) | K15: =44218.15*(1+Reajustes!H28) | L15: =41597.04*(1+Reajustes!H28) | M15: =54790.32*(1+Reajustes!H28) | N15: =0.0*(1+Reajustes!H28) | O15: =SUM(C15:N15)
B16: Alimentação e Lanche | C16: =427.51*(1+Reajustes!H29) | D16: =275.15*(1+Reajustes!H29) | E16: =300.8*(1+Reajustes!H29) | F16: =282.0*(1+Reajustes!H29) | G16: =253.6*(1+Reajustes!H29) | H16: =458.16*(1+Reajustes!H29) | I16: =300.8*(1+Reajustes!H29) | J16: =0.0*(1+Reajustes!H29) | K16: =0.0*(1+Reajustes!H29) | L16: =0.0*(1+Reajustes!H29) | M16: =0.0*(1+Reajustes!H29) | N16: =0.0*(1+Reajustes!H29) | O16: =SUM(C16:N16)
B17: Padaria | C17: =0.0*(1+Reajustes!H30) | D17: =0.0*(1+Reajustes!H30) | E17: =0.0*(1+Reajustes!H30) | F17: =0.0*(1+Reajustes!H30) | G17: =0.0*(1+Reajustes!H30) | H17: =0.0*(1+Reajustes!H30) | I17: =0.0*(1+Reajustes!H30) | J17: =418.0*(1+Reajustes!H30) | K17: =286.39*(1+Reajustes!H30) | L17: =325.1*(1+Reajustes!H30) | M17: =470.2*(1+Reajustes!H30) | N17: =255.75*(1+Reajustes!H30) | O17: =SUM(C17:N17)
B18: Total Despesa com Funcionários | C18: =SUM(C15:C17) | D18: =SUM(D15:D17) | E18: =SUM(E15:E17) | F18: =SUM(F15:F17) | G18: =SUM(G15:G17) | H18: =SUM(H15:H17) | I18: =SUM(I15:I17) | J18: =SUM(J15:J17) | ... O18: =SUM(O15:O17)
B20: Retenções Fiscais
B21: ISS | C21: =3623.35*(1+Reajustes!H31) | D21: =5216.74*(1+Reajustes!H31) | E21: =5333.58*(1+Reajustes!H31) | F21: =3815.81*(1+Reajustes!H31) | G21: =3801.31*(1+Reajustes!H31) | H21: =3744.21*(1+Reajustes!H31) | I21: =579.45*(1+Reajustes!H31) | J21: =4901.8*(1+Reajustes!H31) | K21: =3276.3*(1+Reajustes!H31) | L21: =2817.56*(1+Reajustes!H31) | M21: =3150.41*(1+Reajustes!H31) | N21: =4819.66*(1+Reajustes!H31) | O21: =SUM(C21:N21)
B22: DARF Pis Cofins CSLL | C22: =9758.73*(1+Reajustes!H32) | D22: =9225.67*(1+Reajustes!H32) | E22: =6141.35*(1+Reajustes!H32) | F22: =6039.63*(1+Reajustes!H32) | G22: =6041.45*(1+Reajustes!H32) | H22: =1164.67*(1+Reajustes!H32) | I22: =6718.67*(1+Reajustes!H32) | J22: =9371.71*(1+Reajustes!H32) | K22: =9375.14*(1+Reajustes!H32) | L22: =9373.94*(1+Reajustes!H32) | M22: =8378.55*(1+Reajustes!H32) | N22: =11977.88*(1+Reajustes!H32) | O22: =SUM(C22:N22)
B23: Total Retenções Fiscais | C23: =SUM(C21:C22) | D23: =SUM(D21:D22) | E23: =SUM(E21:E22) | F23: =SUM(F21:F22) | G23: =SUM(G21:G22) | H23: =SUM(H21:H22) | I23: =SUM(I21:I22) | J23: =SUM(J21:J22) | ... O23: =SUM(O21:O22)
B25: Despesa Administrativa
B26: Honorários Administrativos | C26: =1862.0*(1+Reajustes!H33) | D26: =1862.0*(1+Reajustes!H33) | E26: =1862.0*(1+Reajustes!H33) | F26: =1862.0*(1+Reajustes!H33) | G26: =1862.0*(1+Reajustes!H33) | H26: =1862.0*(1+Reajustes!H33) | I26: =1862.0*(1+Reajustes!H33) | J26: =1862.0*(1+Reajustes!H33) | K26: =1862.0*(1+Reajustes!H33) | L26: =1862.0*(1+Reajustes!H33) | M26: =1862.0*(1+Reajustes!H33) | N26: =1960.0*(1+Reajustes!H33) | O26: =SUM(C26:N26)
B27: Honorários Síndico | C27: =3200.0*(1+Reajustes!H34) | D27: =3200.0*(1+Reajustes!H34) | E27: =3200.0*(1+Reajustes!H34) | F27: =3200.0*(1+Reajustes!H34) | G27: =3200.0*(1+Reajustes!H34) | H27: =3200.0*(1+Reajustes!H34) | I27: =3200.0*(1+Reajustes!H34) | J27: =3200.0*(1+Reajustes!H34) | K27: =3200.0*(1+Reajustes!H34) | L27: =3200.0*(1+Reajustes!H34) | M27: =3200.0*(1+Reajustes!H34) | N27: =3200.0*(1+Reajustes!H34) | O27: =SUM(C27:N27)
B28: Despesas Com Correios | C28: =0.0*(1+Reajustes!H35) | D28: =114.6*(1+Reajustes!H35) | E28: =18.4*(1+Reajustes!H35) | F28: =0.0*(1+Reajustes!H35) | G28: =0.0*(1+Reajustes!H35) | H28: =0.0*(1+Reajustes!H35) | I28: =0.0*(1+Reajustes!H35) | J28: =0.0*(1+Reajustes!H35) | K28: =0.0*(1+Reajustes!H35) | L28: =0.0*(1+Reajustes!H35) | M28: =0.0*(1+Reajustes!H35) | N28: =0.0*(1+Reajustes!H35) | O28: =SUM(C28:N28)
B29: Despesas Com Cartório | C29: =0.0*(1+Reajustes!H36) | D29: =114.6*(1+Reajustes!H36) | E29: =0.0*(1+Reajustes!H36) | F29: =342.96*(1+Reajustes!H36) | G29: =0.0*(1+Reajustes!H36) | H29: =161.25*(1+Reajustes!H36) | I29: =99.91*(1+Reajustes!H36) | J29: =0.0*(1+Reajustes!H36) | K29: =0.0*(1+Reajustes!H36) | L29: =0.0*(1+Reajustes!H36) | M29: =0.0*(1+Reajustes!H36) | N29: =0.0*(1+Reajustes!H36) | O29: =SUM(C29:N29)
B30: Despesas Com Material de Expediente | C30: =0.0*(1+Reajustes!H37) | D30: =0.0*(1+Reajustes!H37) | E30: =263.34*(1+Reajustes!H37) | F30: =0.0*(1+Reajustes!H37) | G30: =0.0*(1+Reajustes!H37) | H30: =471.58*(1+Reajustes!H37) | I30: =0.0*(1+Reajustes!H37) | J30: =0.0*(1+Reajustes!H37) | K30: =0.0*(1+Reajustes!H37) | L30: =0.0*(1+Reajustes!H37) | M30: =0.0*(1+Reajustes!H37) | N30: =0.0*(1+Reajustes!H37) | O30: =SUM(C30:N30)
B31: Honorários Advocatícios | C31: =0.0*(1+Reajustes!H38) | D31: =759.0*(1+Reajustes!H38) | E31: =1518.0*(1+Reajustes!H38) | F31: =1518.0*(1+Reajustes!H38) | G31: =1518.0*(1+Reajustes!H38) | H31: =1518.0*(1+Reajustes!H38) | I31: =1518.0*(1+Reajustes!H38) | J31: =1518.0*(1+Reajustes!H38) | K31: =1518.0*(1+Reajustes!H38) | L31: =1518.0*(1+Reajustes!H38) | M31: =1518.0*(1+Reajustes!H38) | N31: =1518.0*(1+Reajustes!H38) | O31: =SUM(C31:N31)
B32: Custas Processuais | C32: =0.0*(1+Reajustes!H39) | D32: =0.0*(1+Reajustes!H39) | E32: =0.0*(1+Reajustes!H39) | F32: =0.0*(1+Reajustes!H39) | G32: =0.0*(1+Reajustes!H39) | H32: =0.0*(1+Reajustes!H39) | I32: =112.28*(1+Reajustes!H39) | J32: =404.74*(1+Reajustes!H39) | K32: =91.56*(1+Reajustes!H39) | L32: =404.74*(1+Reajustes!H39) | M32: =0.0*(1+Reajustes!H39) | N32: =0.0*(1+Reajustes!H39) | O32: =SUM(C32:N32)
B33: Multa-Penalidade | C33: =0.0*(1+Reajustes!H40) | D33: =0.0*(1+Reajustes!H40) | E33: =0.0*(1+Reajustes!H40) | F33: =0.0*(1+Reajustes!H40) | G33: =0.0*(1+Reajustes!H40) | H33: =0.0*(1+Reajustes!H40) | I33: =0.0*(1+Reajustes!H40) | J33: =0.0*(1+Reajustes!H40) | K33: =0.0*(1+Reajustes!H40) | L33: =22.3*(1+Reajustes!H40) | M33: =0.0*(1+Reajustes!H40) | N33: =0.0*(1+Reajustes!H40) | O33: =SUM(C33:N33)
B34: Taxa Antecipação Garantidora | C34: =2939.58*(1+Reajustes!H41) | D34: =3678.04*(1+Reajustes!H41) | E34: =3514.94*(1+Reajustes!H41) | F34: =3459.27*(1+Reajustes!H41) | G34: =3540.76*(1+Reajustes!H41) | H34: =3601.87*(1+Reajustes!H41) | I34: =3601.8*(1+Reajustes!H41) | J34: =3671.78*(1+Reajustes!H41) | K34: =3647.33*(1+Reajustes!H41) | L34: =3577.78*(1+Reajustes!H41) | M34: =3685.29*(1+Reajustes!H41) | N34: =0.0*(1+Reajustes!H41) | O34: =SUM(C34:N34)
B35: Despesa com Deslocamento | C35: =0.0*(1+Reajustes!H42) | D35: =0.0*(1+Reajustes!H42) | E35: =30.63*(1+Reajustes!H42) | F35: =0.0*(1+Reajustes!H42) | G35: =0.0*(1+Reajustes!H42) | H35: =0.0*(1+Reajustes!H42) | I35: =0.0*(1+Reajustes!H42) | J35: =0.0*(1+Reajustes!H42) | K35: =0.0*(1+Reajustes!H42) | L35: =0.0*(1+Reajustes!H42) | M35: =0.0*(1+Reajustes!H42) | N35: =0.0*(1+Reajustes!H42) | O35: =SUM(C35:N35)
B36: Total Despesa Administrativa | C36: =SUM(C26:C35) | D36: =SUM(D26:D35) | E36: =SUM(E26:E35) | F36: =SUM(F26:F35) | G36: =SUM(G26:G35) | H36: =SUM(H26:H35) | I36: =SUM(I26:I35) | J36: =SUM(J26:J35) | ... O36: =SUM(O26:O35)
B38: Manutenção
B39: Contrato Manutenção Elevador | C39: =1452.79*(1+Reajustes!H43) | D39: =1452.79*(1+Reajustes!H43) | E39: =1452.79*(1+Reajustes!H43) | F39: =1452.79*(1+Reajustes!H43) | G39: =1452.79*(1+Reajustes!H43) | H39: =1452.79*(1+Reajustes!H43) | I39: =1452.79*(1+Reajustes!H43) | J39: =1452.79*(1+Reajustes!H43) | K39: =1452.79*(1+Reajustes!H43) | L39: =1452.79*(1+Reajustes!H43) | M39: =1452.79*(1+Reajustes!H43) | N39: =1452.79*(1+Reajustes!H43) | O39: =SUM(C39:N39)
B40: Contrato Manutenção Piscina | C40: =1500.0*(1+Reajustes!H44) | D40: =1800.0*(1+Reajustes!H44) | E40: =1500.0*(1+Reajustes!H44) | F40: =1500.0*(1+Reajustes!H44) | G40: =1500.0*(1+Reajustes!H44) | H40: =1500.0*(1+Reajustes!H44) | I40: =1500.0*(1+Reajustes!H44) | J40: =1500.0*(1+Reajustes!H44) | K40: =1446.0*(1+Reajustes!H44) | L40: =1446.0*(1+Reajustes!H44) | M40: =1446.0*(1+Reajustes!H44) | N40: =1446.0*(1+Reajustes!H44) | O40: =SUM(C40:N40)
B41: Contrato Manutenção Jardinagem | C41: =1100.0*(1+Reajustes!H45) | D41: =1100.0*(1+Reajustes!H45) | E41: =1100.0*(1+Reajustes!H45) | F41: =1100.0*(1+Reajustes!H45) | G41: =1045.0*(1+Reajustes!H45) | H41: =1045.0*(1+Reajustes!H45) | I41: =1045.0*(1+Reajustes!H45) | J41: =1100.0*(1+Reajustes!H45) | K41: =0.0*(1+Reajustes!H45) | L41: =0.0*(1+Reajustes!H45) | M41: =0.0*(1+Reajustes!H45) | N41: =1140.0*(1+Reajustes!H45) | O41: =SUM(C41:N41)
B42: Contrato Manutenção Segurança Eletrônica | C42: =820.0*(1+Reajustes!H46) | D42: =886.54*(1+Reajustes!H46) | E42: =1400.0*(1+Reajustes!H46) | F42: =1400.0*(1+Reajustes!H46) | G42: =1355.48*(1+Reajustes!H46) | H42: =1355.48*(1+Reajustes!H46) | I42: =1355.48*(1+Reajustes!H46) | J42: =1355.48*(1+Reajustes!H46) | K42: =1372.0*(1+Reajustes!H46) | L42: =1372.0*(1+Reajustes!H46) | M42: =1372.0*(1+Reajustes!H46) | N42: =1372.0*(1+Reajustes!H46) | O42: =SUM(C42:N42)
B43: Contrato de Manutenção de Desinsetização | C43: =0.0*(1+Reajustes!H47) | D43: =604.33*(1+Reajustes!H47) | E43: =604.33*(1+Reajustes!H47) | F43: =604.33*(1+Reajustes!H47) | G43: =604.33*(1+Reajustes!H47) | H43: =604.33*(1+Reajustes!H47) | I43: =604.33*(1+Reajustes!H47) | J43: =601.55*(1+Reajustes!H47) | K43: =601.55*(1+Reajustes!H47) | L43: =601.55*(1+Reajustes!H47) | M43: =601.55*(1+Reajustes!H47) | N43: =601.55*(1+Reajustes!H47) | O43: =SUM(C43:N43)
B44: Contrato Manutenção de Segurança | C44: =615.68*(1+Reajustes!H48) | D44: =0.0*(1+Reajustes!H48) | E44: =0.0*(1+Reajustes!H48) | F44: =203.6*(1+Reajustes!H48) | G44: =0.0*(1+Reajustes!H48) | H44: =0.0*(1+Reajustes!H48) | I44: =0.0*(1+Reajustes!H48) | J44: =0.0*(1+Reajustes!H48) | K44: =0.0*(1+Reajustes!H48) | L44: =0.0*(1+Reajustes!H48) | M44: =0.0*(1+Reajustes!H48) | N44: =0.0*(1+Reajustes!H48) | O44: =SUM(C44:N44)
B45: Contrato Manutenção Bombas | C45: =282.17*(1+Reajustes!H49) | D45: =305.68*(1+Reajustes!H49) | E45: =305.81*(1+Reajustes!H49) | F45: =281.85*(1+Reajustes!H49) | G45: =281.91*(1+Reajustes!H49) | H45: =281.85*(1+Reajustes!H49) | I45: =282.0*(1+Reajustes!H49) | J45: =282.0*(1+Reajustes!H49) | K45: =281.91*(1+Reajustes!H49) | L45: =282.0*(1+Reajustes!H49) | M45: =281.82*(1+Reajustes!H49) | N45: =281.94*(1+Reajustes!H49) | O45: =SUM(C45:N45)
B46: Contrato Cx. de Gordura - Fossa e Esgoto | C46: =967.6*(1+Reajustes!H50) | D46: =0.0*(1+Reajustes!H50) | E46: =2085.76*(1+Reajustes!H50) | F46: =967.6*(1+Reajustes!H50) | G46: =967.6*(1+Reajustes!H50) | H46: =967.6*(1+Reajustes!H50) | I46: =2120.59*(1+Reajustes!H50) | J46: =967.6*(1+Reajustes!H50) | K46: =961.1*(1+Reajustes!H50) | L46: =961.1*(1+Reajustes!H50) | M46: =961.1*(1+Reajustes!H50) | N46: =1231.75*(1+Reajustes!H50) | O46: =SUM(C46:N46)
B47: Contrato Manutenção ETE | C47: =0.0*(1+Reajustes!H51) | D47: =967.6*(1+Reajustes!H51) | E47: =0.0*(1+Reajustes!H51) | F47: =0.0*(1+Reajustes!H51) | G47: =0.0*(1+Reajustes!H51) | H47: =0.0*(1+Reajustes!H51) | I47: =0.0*(1+Reajustes!H51) | J47: =0.0*(1+Reajustes!H51) | K47: =0.0*(1+Reajustes!H51) | L47: =0.0*(1+Reajustes!H51) | M47: =0.0*(1+Reajustes!H51) | N47: =0.0*(1+Reajustes!H51) | O47: =SUM(C47:N47)
B48: Total Manutenção | C48: =SUM(C39:C47) | D48: =SUM(D39:D47) | E48: =SUM(E39:E47) | F48: =SUM(F39:F47) | G48: =SUM(G39:G47) | H48: =SUM(H39:H47) | I48: =SUM(I39:I47) | J48: =SUM(J39:J47) | ... O48: =SUM(O39:O47)
B50: Aquisição de Materiais
B51: Material de Limpeza | C51: =1951.93*(1+Reajustes!H52) | D51: =1545.92*(1+Reajustes!H52) | E51: =902.1*(1+Reajustes!H52) | F51: =1799.9*(1+Reajustes!H52) | G51: =1566.73*(1+Reajustes!H52) | H51: =1500.0*(1+Reajustes!H52) | I51: =1573.46*(1+Reajustes!H52) | J51: =1691.15*(1+Reajustes!H52) | K51: =1563.0*(1+Reajustes!H52) | L51: =1493.03*(1+Reajustes!H52) | M51: =1587.67*(1+Reajustes!H52) | N51: =1814.92*(1+Reajustes!H52) | O51: =SUM(C51:N51)
B52: Material Elétrico | C52: =0.0*(1+Reajustes!H53) | D52: =316.0*(1+Reajustes!H53) | E52: =1459.51*(1+Reajustes!H53) | F52: =1145.0*(1+Reajustes!H53) | G52: =1145.0*(1+Reajustes!H53) | H52: =390.0*(1+Reajustes!H53) | I52: =0.0*(1+Reajustes!H53) | J52: =0.0*(1+Reajustes!H53) | K52: =0.0*(1+Reajustes!H53) | L52: =660.0*(1+Reajustes!H53) | M52: =0.0*(1+Reajustes!H53) | N52: =0.0*(1+Reajustes!H53) | O52: =SUM(C52:N52)
B53: Material Hidráulico | C53: =0.0*(1+Reajustes!H54) | D53: =0.0*(1+Reajustes!H54) | E53: =0.0*(1+Reajustes!H54) | F53: =0.0*(1+Reajustes!H54) | G53: =96.89*(1+Reajustes!H54) | H53: =0.0*(1+Reajustes!H54) | I53: =0.0*(1+Reajustes!H54) | J53: =0.0*(1+Reajustes!H54) | K53: =0.0*(1+Reajustes!H54) | L53: =0.0*(1+Reajustes!H54) | M53: =0.0*(1+Reajustes!H54) | N53: =0.0*(1+Reajustes!H54) | O53: =SUM(C53:N53)
B54: Material de Segurança Eletrônica | C54: =1518.17*(1+Reajustes!H55) | D54: =2508.6*(1+Reajustes!H55) | E54: =1885.79*(1+Reajustes!H55) | F54: =1405.88*(1+Reajustes!H55) | G54: =450.0*(1+Reajustes!H55) | H54: =0.0*(1+Reajustes!H55) | I54: =0.0*(1+Reajustes!H55) | J54: =0.0*(1+Reajustes!H55) | K54: =1736.36*(1+Reajustes!H55) | L54: =1936.17*(1+Reajustes!H55) | M54: =3358.38*(1+Reajustes!H55) | N54: =813.98*(1+Reajustes!H55) | O54: =SUM(C54:N54)
B55: Material de Pintura | C55: =546.5*(1+Reajustes!H56) | D55: =546.52*(1+Reajustes!H56) | E55: =627.78*(1+Reajustes!H56) | F55: =1480.7*(1+Reajustes!H56) | G55: =1150.71*(1+Reajustes!H56) | H55: =1151.22*(1+Reajustes!H56) | I55: =34.35*(1+Reajustes!H56) | J55: =771.22*(1+Reajustes!H56) | K55: =0.0*(1+Reajustes!H56) | L55: =0.0*(1+Reajustes!H56) | M55: =0.0*(1+Reajustes!H56) | N55: =0.0*(1+Reajustes!H56) | O55: =SUM(C55:N55)
B56: Material de Construção-Ferramentas | C56: =154.9*(1+Reajustes!H57) | D56: =324.0*(1+Reajustes!H57) | E56: =767.35*(1+Reajustes!H57) | F56: =642.13*(1+Reajustes!H57) | G56: =282.98*(1+Reajustes!H57) | H56: =725.1*(1+Reajustes!H57) | I56: =804.17*(1+Reajustes!H57) | J56: =1148.1*(1+Reajustes!H57) | K56: =275.0*(1+Reajustes!H57) | L56: =1430.5*(1+Reajustes!H57) | M56: =669.0*(1+Reajustes!H57) | N56: =899.5*(1+Reajustes!H57) | O56: =SUM(C56:N56)
B57: Material de Uso e Consumo Condomínio | C57: =0.0*(1+Reajustes!H58) | D57: =120.0*(1+Reajustes!H58) | E57: =774.0*(1+Reajustes!H58) | F57: =358.0*(1+Reajustes!H58) | G57: =332.79*(1+Reajustes!H58) | H57: =0.0*(1+Reajustes!H58) | I57: =293.64*(1+Reajustes!H58) | J57: =141.55*(1+Reajustes!H58) | K57: =1724.66*(1+Reajustes!H58) | L57: =1083.0*(1+Reajustes!H58) | M57: =0.0*(1+Reajustes!H58) | N57: =0.0*(1+Reajustes!H58) | O57: =SUM(C57:N57)
B58: Material de Confraternização-Festa | C58: =500.0*(1+Reajustes!H59) | D58: =0.0*(1+Reajustes!H59) | E58: =0.0*(1+Reajustes!H59) | F58: =0.0*(1+Reajustes!H59) | G58: =0.0*(1+Reajustes!H59) | H58: =0.0*(1+Reajustes!H59) | I58: =2385.24*(1+Reajustes!H59) | J58: =0.0*(1+Reajustes!H59) | K58: =0.0*(1+Reajustes!H59) | L58: =0.0*(1+Reajustes!H59) | M58: =0.0*(1+Reajustes!H59) | N58: =0.0*(1+Reajustes!H59) | O58: =SUM(C58:N58)
B59: Material de Informática | C59: =0.0*(1+Reajustes!H60) | D59: =326.67*(1+Reajustes!H60) | E59: =326.67*(1+Reajustes!H60) | F59: =326.66*(1+Reajustes!H60) | G59: =0.0*(1+Reajustes!H60) | H59: =84.89*(1+Reajustes!H60) | I59: =0.0*(1+Reajustes!H60) | J59: =0.0*(1+Reajustes!H60) | K59: =0.0*(1+Reajustes!H60) | L59: =0.0*(1+Reajustes!H60) | M59: =0.0*(1+Reajustes!H60) | N59: =0.0*(1+Reajustes!H60) | O59: =SUM(C59:N59)
B60: Material de Academia | C60: =0.0*(1+Reajustes!H61) | D60: =0.0*(1+Reajustes!H61) | E60: =0.0*(1+Reajustes!H61) | F60: =0.0*(1+Reajustes!H61) | G60: =0.0*(1+Reajustes!H61) | H60: =0.0*(1+Reajustes!H61) | I60: =10257.7*(1+Reajustes!H61) | J60: =196.27*(1+Reajustes!H61) | K60: =0.0*(1+Reajustes!H61) | L60: =0.0*(1+Reajustes!H61) | M60: =0.0*(1+Reajustes!H61) | N60: =0.0*(1+Reajustes!H61) | O60: =SUM(C60:N60)
B61: Material de Piscina | C61: =0.0*(1+Reajustes!H62) | D61: =192.5*(1+Reajustes!H62) | E61: =198.27*(1+Reajustes!H62) | F61: =0.0*(1+Reajustes!H62) | G61: =0.0*(1+Reajustes!H62) | H61: =0.0*(1+Reajustes!H62) | I61: =0.0*(1+Reajustes!H62) | J61: =0.0*(1+Reajustes!H62) | K61: =0.0*(1+Reajustes!H62) | L61: =0.0*(1+Reajustes!H62) | M61: =0.0*(1+Reajustes!H62) | N61: =0.0*(1+Reajustes!H62) | O61: =SUM(C61:N61)
B62: Material Área de Lazer | C62: =0.0*(1+Reajustes!H63) | D62: =0.0*(1+Reajustes!H63) | E62: =0.0*(1+Reajustes!H63) | F62: =3339.99*(1+Reajustes!H63) | G62: =73.97*(1+Reajustes!H63) | H62: =215.0*(1+Reajustes!H63) | I62: =3785.04*(1+Reajustes!H63) | J62: =0.0*(1+Reajustes!H63) | K62: =0.0*(1+Reajustes!H63) | L62: =0.0*(1+Reajustes!H63) | M62: =0.0*(1+Reajustes!H63) | N62: =0.0*(1+Reajustes!H63) | O62: =SUM(C62:N62)
B63: Tags - Controle de Acesso | C63: =300.0*(1+Reajustes!H64) | D63: =450.0*(1+Reajustes!H64) | E63: =300.0*(1+Reajustes!H64) | F63: =0.0*(1+Reajustes!H64) | G63: =0.0*(1+Reajustes!H64) | H63: =0.0*(1+Reajustes!H64) | I63: =900.0*(1+Reajustes!H64) | J63: =675.0*(1+Reajustes!H64) | K63: =675.0*(1+Reajustes!H64) | L63: =0.0*(1+Reajustes!H64) | M63: =0.0*(1+Reajustes!H64) | N63: =150.0*(1+Reajustes!H64) | O63: =SUM(C63:N63)
B64: Material para Portão | C64: =0.0*(1+Reajustes!H65) | D64: =0.0*(1+Reajustes!H65) | E64: =0.0*(1+Reajustes!H65) | F64: =0.0*(1+Reajustes!H65) | G64: =0.0*(1+Reajustes!H65) | H64: =0.0*(1+Reajustes!H65) | I64: =0.0*(1+Reajustes!H65) | J64: =0.0*(1+Reajustes!H65) | K64: =0.0*(1+Reajustes!H65) | L64: =0.0*(1+Reajustes!H65) | M64: =2658.73*(1+Reajustes!H65) | N64: =1345.9*(1+Reajustes!H65) | O64: =SUM(C64:N64)
B65: Material de Decoração | C65: =0.0*(1+Reajustes!H66) | D65: =0.0*(1+Reajustes!H66) | E65: =0.0*(1+Reajustes!H66) | F65: =0.0*(1+Reajustes!H66) | G65: =2140.0*(1+Reajustes!H66) | H65: =0.0*(1+Reajustes!H66) | I65: =0.0*(1+Reajustes!H66) | J65: =0.0*(1+Reajustes!H66) | K65: =0.0*(1+Reajustes!H66) | L65: =0.0*(1+Reajustes!H66) | M65: =0.0*(1+Reajustes!H66) | N65: =0.0*(1+Reajustes!H66) | O65: =SUM(C65:N65)
B66: Material Salão de Festas | C66: =625.0*(1+Reajustes!H67) | D66: =0.0*(1+Reajustes!H67) | E66: =0.0*(1+Reajustes!H67) | F66: =0.0*(1+Reajustes!H67) | G66: =0.0*(1+Reajustes!H67) | H66: =0.0*(1+Reajustes!H67) | I66: =0.0*(1+Reajustes!H67) | J66: =0.0*(1+Reajustes!H67) | K66: =0.0*(1+Reajustes!H67) | L66: =0.0*(1+Reajustes!H67) | M66: =0.0*(1+Reajustes!H67) | N66: =0.0*(1+Reajustes!H67) | O66: =SUM(C66:N66)
B67: Material de Interfone | C67: =0.0*(1+Reajustes!H68) | D67: =0.0*(1+Reajustes!H68) | E67: =0.0*(1+Reajustes!H68) | F67: =0.0*(1+Reajustes!H68) | G67: =0.0*(1+Reajustes!H68) | H67: =0.0*(1+Reajustes!H68) | I67: =0.0*(1+Reajustes!H68) | J67: =110.0*(1+Reajustes!H68) | K67: =0.0*(1+Reajustes!H68) | L67: =388.16*(1+Reajustes!H68) | M67: =388.16*(1+Reajustes!H68) | N67: =0.0*(1+Reajustes!H68) | O67: =SUM(C67:N67)
B68: Ferramentas-materiais para manutenção | C68: =0.0*(1+Reajustes!H69) | D68: =0.0*(1+Reajustes!H69) | E68: =0.0*(1+Reajustes!H69) | F68: =1048.69*(1+Reajustes!H69) | G68: =0.0*(1+Reajustes!H69) | H68: =0.0*(1+Reajustes!H69) | I68: =0.0*(1+Reajustes!H69) | J68: =771.56*(1+Reajustes!H69) | K68: =391.29*(1+Reajustes!H69) | L68: =0.0*(1+Reajustes!H69) | M68: =420.0*(1+Reajustes!H69) | N68: =0.0*(1+Reajustes!H69) | O68: =SUM(C68:N68)
B69: Material de Sinalização | C69: =0.0*(1+Reajustes!H70) | D69: =0.0*(1+Reajustes!H70) | E69: =0.0*(1+Reajustes!H70) | F69: =0.0*(1+Reajustes!H70) | G69: =0.0*(1+Reajustes!H70) | H69: =692.91*(1+Reajustes!H70) | I69: =794.28*(1+Reajustes!H70) | J69: =579.26*(1+Reajustes!H70) | K69: =579.26*(1+Reajustes!H70) | L69: =0.0*(1+Reajustes!H70) | M69: =449.0*(1+Reajustes!H70) | N69: =458.0*(1+Reajustes!H70) | O69: =SUM(C69:N69)
B70: Material de Extintor | C70: =0.0*(1+Reajustes!H71) | D70: =0.0*(1+Reajustes!H71) | E70: =0.0*(1+Reajustes!H71) | F70: =0.0*(1+Reajustes!H71) | G70: =0.0*(1+Reajustes!H71) | H70: =0.0*(1+Reajustes!H71) | I70: =0.0*(1+Reajustes!H71) | J70: =0.0*(1+Reajustes!H71) | K70: =0.0*(1+Reajustes!H71) | L70: =0.0*(1+Reajustes!H71) | M70: =1609.5*(1+Reajustes!H71) | N70: =1609.5*(1+Reajustes!H71) | O70: =SUM(C70:N70)
B71: Total Aquisição de Materiais | C71: =SUM(C51:C70) | D71: =SUM(D51:D70) | E71: =SUM(E51:E70) | F71: =SUM(F51:F70) | G71: =SUM(G51:G70) | H71: =SUM(H51:H70) | I71: =SUM(I51:I70) | J71: =SUM(J51:J70) | ... O71: =SUM(O51:O70)
B73: Serviços
B74: Seguro Condominial | C74: =1273.65*(1+Reajustes!H72) | D74: =1273.72*(1+Reajustes!H72) | E74: =0.0*(1+Reajustes!H72) | F74: =0.0*(1+Reajustes!H72) | G74: =0.0*(1+Reajustes!H72) | H74: =0.0*(1+Reajustes!H72) | I74: =0.0*(1+Reajustes!H72) | J74: =0.0*(1+Reajustes!H72) | K74: =0.0*(1+Reajustes!H72) | L74: =1380.14*(1+Reajustes!H72) | M74: =1337.34*(1+Reajustes!H72) | N74: =1337.34*(1+Reajustes!H72) | O74: =SUM(C74:N74)
B75: Serviço de Pintura | C75: =0.0*(1+Reajustes!H73) | D75: =0.0*(1+Reajustes!H73) | E75: =0.0*(1+Reajustes!H73) | F75: =0.0*(1+Reajustes!H73) | G75: =0.0*(1+Reajustes!H73) | H75: =0.0*(1+Reajustes!H73) | I75: =0.0*(1+Reajustes!H73) | J75: =500.0*(1+Reajustes!H73) | K75: =0.0*(1+Reajustes!H73) | L75: =0.0*(1+Reajustes!H73) | M75: =0.0*(1+Reajustes!H73) | N75: =0.0*(1+Reajustes!H73) | O75: =SUM(C75:N75)
B76: Serviço Elétrico | C76: =0.0*(1+Reajustes!H74) | D76: =0.0*(1+Reajustes!H74) | E76: =0.0*(1+Reajustes!H74) | F76: =0.0*(1+Reajustes!H74) | G76: =0.0*(1+Reajustes!H74) | H76: =0.0*(1+Reajustes!H74) | I76: =0.0*(1+Reajustes!H74) | J76: =0.0*(1+Reajustes!H74) | K76: =1700.5*(1+Reajustes!H74) | L76: =0.0*(1+Reajustes!H74) | M76: =612.75*(1+Reajustes!H74) | N76: =0.0*(1+Reajustes!H74) | O76: =SUM(C76:N76)
B77: Serviço de Engenharia | C77: =0.0*(1+Reajustes!H75) | D77: =0.0*(1+Reajustes!H75) | E77: =0.0*(1+Reajustes!H75) | F77: =533.1*(1+Reajustes!H75) | G77: =0.0*(1+Reajustes!H75) | H77: =0.0*(1+Reajustes!H75) | I77: =0.0*(1+Reajustes!H75) | J77: =9840.0*(1+Reajustes!H75) | K77: =0.0*(1+Reajustes!H75) | L77: =0.0*(1+Reajustes!H75) | M77: =0.0*(1+Reajustes!H75) | N77: =0.0*(1+Reajustes!H75) | O77: =SUM(C77:N77)
B78: Serviço de Desinsetização | C78: =0.0*(1+Reajustes!H76) | D78: =0.0*(1+Reajustes!H76) | E78: =0.0*(1+Reajustes!H76) | F78: =0.0*(1+Reajustes!H76) | G78: =0.0*(1+Reajustes!H76) | H78: =0.0*(1+Reajustes!H76) | I78: =0.0*(1+Reajustes!H76) | J78: =285.0*(1+Reajustes!H76) | K78: =0.0*(1+Reajustes!H76) | L78: =0.0*(1+Reajustes!H76) | M78: =0.0*(1+Reajustes!H76) | N78: =0.0*(1+Reajustes!H76) | O78: =SUM(C78:N78)
B79: Serviço Gráficos | C79: =0.0*(1+Reajustes!H77) | D79: =0.0*(1+Reajustes!H77) | E79: =0.0*(1+Reajustes!H77) | F79: =115.0*(1+Reajustes!H77) | G79: =0.0*(1+Reajustes!H77) | H79: =0.0*(1+Reajustes!H77) | I79: =0.0*(1+Reajustes!H77) | J79: =0.0*(1+Reajustes!H77) | K79: =0.0*(1+Reajustes!H77) | L79: =0.0*(1+Reajustes!H77) | M79: =132.0*(1+Reajustes!H77) | N79: =0.0*(1+Reajustes!H77) | O79: =SUM(C79:N79)
B80: Serviço de Locação | C80: =250.0*(1+Reajustes!H78) | D80: =0.0*(1+Reajustes!H78) | E80: =350.0*(1+Reajustes!H78) | F80: =670.0*(1+Reajustes!H78) | G80: =0.0*(1+Reajustes!H78) | H80: =0.0*(1+Reajustes!H78) | I80: =400.44*(1+Reajustes!H78) | J80: =0.0*(1+Reajustes!H78) | K80: =0.0*(1+Reajustes!H78) | L80: =0.0*(1+Reajustes!H78) | M80: =0.0*(1+Reajustes!H78) | N80: =0.0*(1+Reajustes!H78) | O80: =SUM(C80:N80)
B81: Serviço de Chaveiro | C81: =0.0*(1+Reajustes!H79) | D81: =0.0*(1+Reajustes!H79) | E81: =130.0*(1+Reajustes!H79) | F81: =0.0*(1+Reajustes!H79) | G81: =0.0*(1+Reajustes!H79) | H81: =0.0*(1+Reajustes!H79) | I81: =0.0*(1+Reajustes!H79) | J81: =0.0*(1+Reajustes!H79) | K81: =0.0*(1+Reajustes!H79) | L81: =0.0*(1+Reajustes!H79) | M81: =0.0*(1+Reajustes!H79) | N81: =0.0*(1+Reajustes!H79) | O81: =SUM(C81:N81)
B82: Serviço de Serralheria | C82: =0.0*(1+Reajustes!H80) | D82: =0.0*(1+Reajustes!H80) | E82: =600.0*(1+Reajustes!H80) | F82: =0.0*(1+Reajustes!H80) | G82: =7617.0*(1+Reajustes!H80) | H82: =850.0*(1+Reajustes!H80) | I82: =850.0*(1+Reajustes!H80) | J82: =200.0*(1+Reajustes!H80) | K82: =2000.0*(1+Reajustes!H80) | L82: =0.0*(1+Reajustes!H80) | M82: =0.0*(1+Reajustes!H80) | N82: =1800.0*(1+Reajustes!H80) | O82: =SUM(C82:N82)
B83: Serviço Hidráulico | C83: =2700.0*(1+Reajustes!H81) | D83: =150.0*(1+Reajustes!H81) | E83: =250.0*(1+Reajustes!H81) | F83: =0.0*(1+Reajustes!H81) | G83: =0.0*(1+Reajustes!H81) | H83: =0.0*(1+Reajustes!H81) | I83: =0.0*(1+Reajustes!H81) | J83: =4000.0*(1+Reajustes!H81) | K83: =0.0*(1+Reajustes!H81) | L83: =0.0*(1+Reajustes!H81) | M83: =0.0*(1+Reajustes!H81) | N83: =0.0*(1+Reajustes!H81) | O83: =SUM(C83:N83)
B84: Serviço de Informática- Internet | C84: =0.0*(1+Reajustes!H82) | D84: =0.0*(1+Reajustes!H82) | E84: =0.0*(1+Reajustes!H82) | F84: =90.0*(1+Reajustes!H82) | G84: =0.0*(1+Reajustes!H82) | H84: =38.0*(1+Reajustes!H82) | I84: =50.0*(1+Reajustes!H82) | J84: =0.0*(1+Reajustes!H82) | K84: =0.0*(1+Reajustes!H82) | L84: =120.0*(1+Reajustes!H82) | M84: =0.0*(1+Reajustes!H82) | N84: =120.0*(1+Reajustes!H82) | O84: =SUM(C84:N84)
B85: Serviço em Portão | C85: =0.0*(1+Reajustes!H83) | D85: =0.0*(1+Reajustes!H83) | E85: =150.0*(1+Reajustes!H83) | F85: =0.0*(1+Reajustes!H83) | G85: =0.0*(1+Reajustes!H83) | H85: =1268.15*(1+Reajustes!H83) | I85: =0.0*(1+Reajustes!H83) | J85: =0.0*(1+Reajustes!H83) | K85: =0.0*(1+Reajustes!H83) | L85: =0.0*(1+Reajustes!H83) | M85: =0.0*(1+Reajustes!H83) | N85: =0.0*(1+Reajustes!H83) | O85: =SUM(C85:N85)
B86: Serviço de Jardinagem | C86: =0.0*(1+Reajustes!H84) | D86: =500.0*(1+Reajustes!H84) | E86: =700.0*(1+Reajustes!H84) | F86: =700.0*(1+Reajustes!H84) | G86: =500.0*(1+Reajustes!H84) | H86: =500.0*(1+Reajustes!H84) | I86: =500.0*(1+Reajustes!H84) | J86: =500.0*(1+Reajustes!H84) | K86: =500.0*(1+Reajustes!H84) | L86: =0.0*(1+Reajustes!H84) | M86: =0.0*(1+Reajustes!H84) | N86: =0.0*(1+Reajustes!H84) | O86: =SUM(C86:N86)
B87: Serviço de Reparo | C87: =0.0*(1+Reajustes!H85) | D87: =0.0*(1+Reajustes!H85) | E87: =0.0*(1+Reajustes!H85) | F87: =0.0*(1+Reajustes!H85) | G87: =0.0*(1+Reajustes!H85) | H87: =0.0*(1+Reajustes!H85) | I87: =0.0*(1+Reajustes!H85) | J87: =220.0*(1+Reajustes!H85) | K87: =1783.6*(1+Reajustes!H85) | L87: =0.0*(1+Reajustes!H85) | M87: =0.0*(1+Reajustes!H85) | N87: =0.0*(1+Reajustes!H85) | O87: =SUM(C87:N87)
B88: Serviço de Marcenária | C88: =0.0*(1+Reajustes!H86) | D88: =0.0*(1+Reajustes!H86) | E88: =0.0*(1+Reajustes!H86) | F88: =0.0*(1+Reajustes!H86) | G88: =500.0*(1+Reajustes!H86) | H88: =600.0*(1+Reajustes!H86) | I88: =0.0*(1+Reajustes!H86) | J88: =0.0*(1+Reajustes!H86) | K88: =0.0*(1+Reajustes!H86) | L88: =0.0*(1+Reajustes!H86) | M88: =0.0*(1+Reajustes!H86) | N88: =0.0*(1+Reajustes!H86) | O88: =SUM(C88:N88)
B89: Serviço de Descupinização | C89: =0.0*(1+Reajustes!H87) | D89: =0.0*(1+Reajustes!H87) | E89: =0.0*(1+Reajustes!H87) | F89: =0.0*(1+Reajustes!H87) | G89: =0.0*(1+Reajustes!H87) | H89: =0.0*(1+Reajustes!H87) | I89: =0.0*(1+Reajustes!H87) | J89: =0.0*(1+Reajustes!H87) | K89: =0.0*(1+Reajustes!H87) | L89: =0.0*(1+Reajustes!H87) | M89: =0.0*(1+Reajustes!H87) | N89: =731.64*(1+Reajustes!H87) | O89: =SUM(C89:N89)
B90: Serviço Manutenção | C90: =0.0*(1+Reajustes!H88) | D90: =0.0*(1+Reajustes!H88) | E90: =0.0*(1+Reajustes!H88) | F90: =0.0*(1+Reajustes!H88) | G90: =1504.16*(1+Reajustes!H88) | H90: =0.0*(1+Reajustes!H88) | I90: =1316.25*(1+Reajustes!H88) | J90: =972.0*(1+Reajustes!H88) | K90: =0.0*(1+Reajustes!H88) | L90: =0.0*(1+Reajustes!H88) | M90: =0.0*(1+Reajustes!H88) | N90: =0.0*(1+Reajustes!H88) | O90: =SUM(C90:N90)
B91: Serviço na Área de Lazer | C91: =0.0*(1+Reajustes!H89) | D91: =0.0*(1+Reajustes!H89) | E91: =0.0*(1+Reajustes!H89) | F91: =0.0*(1+Reajustes!H89) | G91: =0.0*(1+Reajustes!H89) | H91: =0.0*(1+Reajustes!H89) | I91: =650.0*(1+Reajustes!H89) | J91: =0.0*(1+Reajustes!H89) | K91: =0.0*(1+Reajustes!H89) | L91: =0.0*(1+Reajustes!H89) | M91: =0.0*(1+Reajustes!H89) | N91: =0.0*(1+Reajustes!H89) | O91: =SUM(C91:N91)
B92: Obras-Melhorias | C92: =0.0*(1+Reajustes!H90) | D92: =0.0*(1+Reajustes!H90) | E92: =0.0*(1+Reajustes!H90) | F92: =0.0*(1+Reajustes!H90) | G92: =0.0*(1+Reajustes!H90) | H92: =0.0*(1+Reajustes!H90) | I92: =0.0*(1+Reajustes!H90) | J92: =0.0*(1+Reajustes!H90) | K92: =40000.0*(1+Reajustes!H90) | L92: =45200.0*(1+Reajustes!H90) | M92: =40000.0*(1+Reajustes!H90) | N92: =3900.0*(1+Reajustes!H90) | O92: =SUM(C92:N92)
B93: Serviço Segurança Eletrônica | C93: =0.0*(1+Reajustes!H91) | D93: =0.0*(1+Reajustes!H91) | E93: =300.0*(1+Reajustes!H91) | F93: =549.5*(1+Reajustes!H91) | G93: =549.5*(1+Reajustes!H91) | H93: =549.5*(1+Reajustes!H91) | I93: =0.0*(1+Reajustes!H91) | J93: =0.0*(1+Reajustes!H91) | K93: =0.0*(1+Reajustes!H91) | L93: =0.0*(1+Reajustes!H91) | M93: =339.85*(1+Reajustes!H91) | N93: =339.85*(1+Reajustes!H91) | O93: =SUM(C93:N93)
B94: Serviço de Reparo na bomba | C94: =973.18*(1+Reajustes!H92) | D94: =1453.21*(1+Reajustes!H92) | E94: =410.89*(1+Reajustes!H92) | F94: =410.92*(1+Reajustes!H92) | G94: =0.0*(1+Reajustes!H92) | H94: =0.0*(1+Reajustes!H92) | I94: =0.0*(1+Reajustes!H92) | J94: =533.24*(1+Reajustes!H92) | K94: =533.24*(1+Reajustes!H92) | L94: =533.24*(1+Reajustes!H92) | M94: =533.25*(1+Reajustes!H92) | N94: =0.0*(1+Reajustes!H92) | O94: =SUM(C94:N94)
B95: Serviço de Vistoria | C95: =0.0*(1+Reajustes!H93) | D95: =0.0*(1+Reajustes!H93) | E95: =0.0*(1+Reajustes!H93) | F95: =0.0*(1+Reajustes!H93) | G95: =0.0*(1+Reajustes!H93) | H95: =0.0*(1+Reajustes!H93) | I95: =1230.0*(1+Reajustes!H93) | J95: =0.0*(1+Reajustes!H93) | K95: =0.0*(1+Reajustes!H93) | L95: =0.0*(1+Reajustes!H93) | M95: =0.0*(1+Reajustes!H93) | N95: =0.0*(1+Reajustes!H93) | O95: =SUM(C95:N95)
B96: Serviço de Reparo de Elevador | C96: =2230.66*(1+Reajustes!H94) | D96: =1803.16*(1+Reajustes!H94) | E96: =2935.56*(1+Reajustes!H94) | F96: =2369.36*(1+Reajustes!H94) | G96: =2369.36*(1+Reajustes!H94) | H96: =566.2*(1+Reajustes!H94) | I96: =0.0*(1+Reajustes!H94) | J96: =0.0*(1+Reajustes!H94) | K96: =627.0*(1+Reajustes!H94) | L96: =0.0*(1+Reajustes!H94) | M96: =0.0*(1+Reajustes!H94) | N96: =442.94*(1+Reajustes!H94) | O96: =SUM(C96:N96)
B97: Serviço de Manutenção Extintores | C97: =1404.0*(1+Reajustes!H95) | D97: =0.0*(1+Reajustes!H95) | E97: =0.0*(1+Reajustes!H95) | F97: =0.0*(1+Reajustes!H95) | G97: =0.0*(1+Reajustes!H95) | H97: =0.0*(1+Reajustes!H95) | I97: =0.0*(1+Reajustes!H95) | J97: =0.0*(1+Reajustes!H95) | K97: =0.0*(1+Reajustes!H95) | L97: =0.0*(1+Reajustes!H95) | M97: =0.0*(1+Reajustes!H95) | N97: =0.0*(1+Reajustes!H95) | O97: =SUM(C97:N97)
B98: Serviço Prestados | C98: =0.0*(1+Reajustes!H96) | D98: =0.0*(1+Reajustes!H96) | E98: =681.49*(1+Reajustes!H96) | F98: =0.0*(1+Reajustes!H96) | G98: =0.0*(1+Reajustes!H96) | H98: =0.0*(1+Reajustes!H96) | I98: =0.0*(1+Reajustes!H96) | J98: =0.0*(1+Reajustes!H96) | K98: =0.0*(1+Reajustes!H96) | L98: =0.0*(1+Reajustes!H96) | M98: =0.0*(1+Reajustes!H96) | N98: =0.0*(1+Reajustes!H96) | O98: =SUM(C98:N98)
B99: Serviço de Comunicação Visual | C99: =600.0*(1+Reajustes!H97) | D99: =500.0*(1+Reajustes!H97) | E99: =500.0*(1+Reajustes!H97) | F99: =0.0*(1+Reajustes!H97) | G99: =0.0*(1+Reajustes!H97) | H99: =0.0*(1+Reajustes!H97) | I99: =0.0*(1+Reajustes!H97) | J99: =0.0*(1+Reajustes!H97) | K99: =0.0*(1+Reajustes!H97) | L99: =0.0*(1+Reajustes!H97) | M99: =0.0*(1+Reajustes!H97) | N99: =0.0*(1+Reajustes!H97) | O99: =SUM(C99:N99)
B100: Serviço de Ar Condicionado | C100: =0.0*(1+Reajustes!H98) | D100: =500.0*(1+Reajustes!H98) | E100: =0.0*(1+Reajustes!H98) | F100: =0.0*(1+Reajustes!H98) | G100: =0.0*(1+Reajustes!H98) | H100: =0.0*(1+Reajustes!H98) | I100: =0.0*(1+Reajustes!H98) | J100: =0.0*(1+Reajustes!H98) | K100: =280.0*(1+Reajustes!H98) | L100: =0.0*(1+Reajustes!H98) | M100: =0.0*(1+Reajustes!H98) | N100: =0.0*(1+Reajustes!H98) | O100: =SUM(C100:N100)
B101: Serviço de Frete | C101: =0.0*(1+Reajustes!H99) | D101: =0.0*(1+Reajustes!H99) | E101: =0.0*(1+Reajustes!H99) | F101: =0.0*(1+Reajustes!H99) | G101: =0.0*(1+Reajustes!H99) | H101: =0.0*(1+Reajustes!H99) | I101: =0.0*(1+Reajustes!H99) | J101: =0.0*(1+Reajustes!H99) | K101: =850.0*(1+Reajustes!H99) | L101: =0.0*(1+Reajustes!H99) | M101: =0.0*(1+Reajustes!H99) | N101: =0.0*(1+Reajustes!H99) | O101: =SUM(C101:N101)
B102: Serviço de Reforma Móveis e Utensílios | C102: =0.0*(1+Reajustes!H100) | D102: =0.0*(1+Reajustes!H100) | E102: =0.0*(1+Reajustes!H100) | F102: =0.0*(1+Reajustes!H100) | G102: =0.0*(1+Reajustes!H100) | H102: =0.0*(1+Reajustes!H100) | I102: =0.0*(1+Reajustes!H100) | J102: =0.0*(1+Reajustes!H100) | K102: =1795.5*(1+Reajustes!H100) | L102: =0.0*(1+Reajustes!H100) | M102: =0.0*(1+Reajustes!H100) | N102: =0.0*(1+Reajustes!H100) | O102: =SUM(C102:N102)
B103: Serviço em Aparelho de Academia | C103: =0.0*(1+Reajustes!H101) | D103: =0.0*(1+Reajustes!H101) | E103: =0.0*(1+Reajustes!H101) | F103: =0.0*(1+Reajustes!H101) | G103: =0.0*(1+Reajustes!H101) | H103: =0.0*(1+Reajustes!H101) | I103: =0.0*(1+Reajustes!H101) | J103: =176.38*(1+Reajustes!H101) | K103: =0.0*(1+Reajustes!H101) | L103: =274.37*(1+Reajustes!H101) | M103: =500.0*(1+Reajustes!H101) | N103: =0.0*(1+Reajustes!H101) | O103: =SUM(C103:N103)
B104: Serviço Manutenção de Caixa d água | C104: =0.0*(1+Reajustes!H102) | D104: =0.0*(1+Reajustes!H102) | E104: =0.0*(1+Reajustes!H102) | F104: =0.0*(1+Reajustes!H102) | G104: =0.0*(1+Reajustes!H102) | H104: =0.0*(1+Reajustes!H102) | I104: =0.0*(1+Reajustes!H102) | J104: =0.0*(1+Reajustes!H102) | K104: =0.0*(1+Reajustes!H102) | L104: =0.0*(1+Reajustes!H102) | M104: =550.0*(1+Reajustes!H102) | N104: =0.0*(1+Reajustes!H102) | O104: =SUM(C104:N104)
B105: Serviço Eletrônico Obra | C105: =0.0*(1+Reajustes!H103) | D105: =0.0*(1+Reajustes!H103) | E105: =0.0*(1+Reajustes!H103) | F105: =0.0*(1+Reajustes!H103) | G105: =220.0*(1+Reajustes!H103) | H105: =0.0*(1+Reajustes!H103) | I105: =0.0*(1+Reajustes!H103) | J105: =0.0*(1+Reajustes!H103) | K105: =0.0*(1+Reajustes!H103) | L105: =0.0*(1+Reajustes!H103) | M105: =0.0*(1+Reajustes!H103) | N105: =0.0*(1+Reajustes!H103) | O105: =SUM(C105:N105)
B106: Serviços - Obra Fachada | C106: =0.0*(1+Reajustes!H104) | D106: =0.0*(1+Reajustes!H104) | E106: =0.0*(1+Reajustes!H104) | F106: =0.0*(1+Reajustes!H104) | G106: =0.0*(1+Reajustes!H104) | H106: =0.0*(1+Reajustes!H104) | I106: =0.0*(1+Reajustes!H104) | J106: =0.0*(1+Reajustes!H104) | K106: =0.0*(1+Reajustes!H104) | L106: =0.0*(1+Reajustes!H104) | M106: =0.0*(1+Reajustes!H104) | N106: =40000.0*(1+Reajustes!H104) | O106: =SUM(C106:N106)
B107: Serviços - Obra Telhado | C107: =0.0*(1+Reajustes!H105) | D107: =0.0*(1+Reajustes!H105) | E107: =0.0*(1+Reajustes!H105) | F107: =0.0*(1+Reajustes!H105) | G107: =0.0*(1+Reajustes!H105) | H107: =0.0*(1+Reajustes!H105) | I107: =0.0*(1+Reajustes!H105) | J107: =0.0*(1+Reajustes!H105) | K107: =0.0*(1+Reajustes!H105) | L107: =0.0*(1+Reajustes!H105) | M107: =1100.0*(1+Reajustes!H105) | N107: =1000.0*(1+Reajustes!H105) | O107: =SUM(C107:N107)
B108: Total Serviços | C108: =SUM(C74:C107) | D108: =SUM(D74:D107) | E108: =SUM(E74:E107) | F108: =SUM(F74:F107) | G108: =SUM(G74:G107) | H108: =SUM(H74:H107) | I108: =SUM(I74:I107) | J108: =SUM(J74:J107) | ... O108: =SUM(O74:O107)
...

Sheet Resumo Assembleia
B2: PREVISÃO ORÇAMENTÁRIA 2026
B3: Condomínio Naturale Residencial — Base: Realizado Superlógica
B5: RESUMO FINANCEIRO 2026
C7: Despesa Operacional Anual (base do rateio)
C8: ='Previsao Anual'!E122
C10: Fundo de Reserva (5%) — fora do rateio
C11: =C8*0.05
C13: Total a Ratear no Ano (apenas operacional)
C14: =C8
B17: MODO DE RATEIO
C19: Modo de cálculo: | D19: Fração Ideal
C21: Apartamentos: | D21: 0
C22: Coberturas: | D22: 0
C23: Fator da Cobertura: | D23: 1.5
C24: Total de Unidades (igualitário): | D24: 0
C25: Soma das Frações (deve fechar 1 ou 100%): | D25: =SUM('Frações'!C2:C100000)
C27: Unidades Equivalentes: | D27: =D21+D22*D23
C29: Despesa Mensal a Ratear: | D29: =C14/12
B31: TAXA MENSAL RESULTANTE
C33: Taxa Mensal Média por Unidade: | D33: =IFERROR(IF(D19="Unidades Equivalentes",D29/D27,IF(D19="Igualitário",D29/D24,D29/264)),0)
C34: Taxa Mensal por Cobertura: | D34: =IFERROR(IF(D19="Unidades Equivalentes",D33*D23,D33),0)
C36: No modo Fração Ideal, a taxa de cada unidade = Despesa Mensal × Fração da unidade. Veja a aba 'Frações' (uma linha por unidade).
B40: CUSTO MENSAL POR CATEGORIA
C41: Categoria | D41: Anual (R$) | E41: Mensal (R$)
C42: Despesas Financeiras | D42: ='Previsao Anual'!E12 | E42: =D42/12
C43: Despesa com Funcionários | D43: ='Previsao Anual'!E18 | E43: =D43/12
C44: Retenções Fiscais | D44: ='Previsao Anual'!E23 | E44: =D44/12
C45: Despesa Administrativa | D45: ='Previsao Anual'!E36 | E45: =D45/12
C46: Manutenção | D46: ='Previsao Anual'!E48 | E46: =D46/12
C47: Aquisição de Materiais | D47: ='Previsao Anual'!E71 | E47: =D47/12
C48: Serviços | D48: ='Previsao Anual'!E108 | E48: =D48/12
C49: Investimento e Equipamentos | D49: ='Previsao Anual'!E116 | E49: =D49/12
C50: Taxas e Recolhimentos | D50: ='Previsao Anual'!E120 | E50: =D50/12
C51: TOTAL GERAL | D51: =SUM(D42:D50) | E51: =D51/12

Sheet Frações
B1: Unidade | C1: Fração | D1: Taxa Mensal (R$)
B2: Apto 0101-1 | C2: 0.004226 | D2: ='Resumo Assembleia'!D29*C2
B3: Apto 0102-1 | C3: 0.004226 | D3: ='Resumo Assembleia'!D29*C3
B4: Apto 0103-1 | C4: 0.003388 | D4: ='Resumo Assembleia'!D29*C4
B5: Apto 0104-1 | C5: 0.003201 | D5: ='Resumo Assembleia'!D29*C5
B6: Apto 0105-1 | C6: 0.004226 | D6: ='Resumo Assembleia'!D29*C6
B7: Apto 0106-1 | C7: 0.004226 | D7: ='Resumo Assembleia'!D29*C7
B8: Apto 0107-1 | C8: 0.003201 | D8: ='Resumo Assembleia'!D29*C8
B9: Apto 0108-1 | C9: 0.003388 | D9: ='Resumo Assembleia'!D29*C9
B10: Apto 0201-1 | C10: 0.004226 | D10: ='Resumo Assembleia'!D29*C10
B11: Apto 0202-1 | C11: 0.004226 | D11: ='Resumo Assembleia'!D29*C11
B12: Apto 0203-1 | C12: 0.003388 | D12: ='Resumo Assembleia'!D29*C12
B13: Apto 0204-1 | C13: 0.003201 | D13: ='Resumo Assembleia'!D29*C13
B14: Apto 0205-1 | C14: 0.004226 | D14: ='Resumo Assembleia'!D29*C14
B15: Apto 0206-1 | C15: 0.004226 | D15: ='Resumo Assembleia'!D29*C15
B16: Apto 0207-1 | C16: 0.003201 | D16: ='Resumo Assembleia'!D29*C16
B17: Apto 0208-1 | C17: 0.003388 | D17: ='Resumo Assembleia'!D29*C17
B18: Apto 0301-1 | C18: 0.004226 | D18: ='Resumo Assembleia'!D29*C18
B19: Apto 0302-1 | C19: 0.004226 | D19: ='Resumo Assembleia'!D29*C19
B20: Apto 0303-1 | C20: 0.003388 | D20: ='Resumo Assembleia'!D29*C20
B21: Apto 0304-1 | C21: 0.003201 | D21: ='Resumo Assembleia'!D29*C21
B22: Apto 0305-1 | C22: 0.004226 | D22: ='Resumo Assembleia'!D29*C22
B23: Apto 0306-1 | C23: 0.004226 | D23: ='Resumo Assembleia'!D29*C23
B24: Apto 0307-1 | C24: 0.003201 | D24: ='Resumo Assembleia'!D29*C24
B25: Apto 0308-1 | C25: 0.003388 | D25: ='Resumo Assembleia'!D29*C25
B26: Apto 0401-1 | C26: 0.004226 | D26: ='Resumo Assembleia'!D29*C26
B27: Apto 0402-1 | C27: 0.004226 | D27: ='Resumo Assembleia'!D29*C27
B28: Apto 0403-1 | C28: 0.003388 | D28: ='Resumo Assembleia'!D29*C28
B29: Apto 0404-1 | C29: 0.003201 | D29: ='Resumo Assembleia'!D29*C29
B30: Apto 0405-1 | C30: 0.004226 | D30: ='Resumo Assembleia'!D29*C30
B31: Apto 0406-1 | C31: 0.004226 | D31: ='Resumo Assembleia'!D29*C31
B32: Apto 0407-1 | C32: 0.003201 | D32: ='Resumo Assembleia'!D29*C32
B33: Apto 0408-1 | C33: 0.003388 | D33: ='Resumo Assembleia'!D29*C33
B34: Apto 0501-1 | C34: 0.004226 | D34: ='Resumo Assembleia'!D29*C34
B35: Apto 0502-1 | C35: 0.004226 | D35: ='Resumo Assembleia'!D29*C35
B36: Apto 0503-1 | C36: 0.003388 | D36: ='Resumo Assembleia'!D29*C36
B37: Apto 0504-1 | C37: 0.003201 | D37: ='Resumo Assembleia'!D29*C37
B38: Apto 0505-1 | C38: 0.004226 | D38: ='Resumo Assembleia'!D29*C38
B39: Apto 0506-1 | C39: 0.004226 | D39: ='Resumo Assembleia'!D29*C39
B40: Apto 0507-1 | C40: 0.003201 | D40: ='Resumo Assembleia'!D29*C40
B41: Apto 0508-1 | C41: 0.003388 | D41: ='Resumo Assembleia'!D29*C41
B42: Apto 0601-1 | C42: 0.004226 | D42: ='Resumo Assembleia'!D29*C42
B43: Apto 0602-1 | C43: 0.004226 | D43: ='Resumo Assembleia'!D29*C43
B44: Apto 0603-1 | C44: 0.003388 | D44: ='Resumo Assembleia'!D29*C44
B45: Apto 0604-1 | C45: 0.003201 | D45: ='Resumo Assembleia'!D29*C45
B46: Apto 0605-1 | C46: 0.004226 | D46: ='Resumo Assembleia'!D29*C46
B47: Apto 0606-1 | C47: 0.004226 | D47: ='Resumo Assembleia'!D29*C47
B48: Apto 0607-1 | C48: 0.003201 | D48: ='Resumo Assembleia'!D29*C48
B49: Apto 0608-1 | C49: 0.003388 | D49: ='Resumo Assembleia'!D29*C49
B50: Apto 0701-1 | C50: 0.004226 | D50: ='Resumo Assembleia'!D29*C50
B51: Apto 0702-1 | C51: 0.004226 | D51: ='Resumo Assembleia'!D29*C51
B52: Apto 0703-1 | C52: 0.003388 | D52: ='Resumo Assembleia'!D29*C52
B53: Apto 0704-1 | C53: 0.003201 | D53: ='Resumo Assembleia'!D29*C53
B54: Apto 0705-1 | C54: 0.004226 | D54: ='Resumo Assembleia'!D29*C54
B55: Apto 0706-1 | C55: 0.004226 | D55: ='Resumo Assembleia'!D29*C55
B56: Apto 0707-1 | C56: 0.003201 | D56: ='Resumo Assembleia'!D29*C56
B57: Apto 0708-1 | C57: 0.003388 | D57: ='Resumo Assembleia'!D29*C57
B58: Apto 0801-1 | C58: 0.004226 | D58: ='Resumo Assembleia'!D29*C58
B59: Apto 0802-1 | C59: 0.004226 | D59: ='Resumo Assembleia'!D29*C59
B60: Apto 0803-1 | C60: 0.003535 | D60: ='Resumo Assembleia'!D29*C60
B61: Apto 0804-1 | C61: 0.003201 | D61: ='Resumo Assembleia'!D29*C61
B62: Apto 0805-1 | C62: 0.004226 | D62: ='Resumo Assembleia'!D29*C62
B63: Apto 0806-1 | C63: 0.004226 | D63: ='Resumo Assembleia'!D29*C63
B64: Apto 0807-1 | C64: 0.003201 | D64: ='Resumo Assembleia'!D29*C64
B65: Apto 0808-1 | C65: 0.003535 | D65: ='Resumo Assembleia'!D29*C65
B66: Apto 0901-1 | C66: 0.004226 | D66: ='Resumo Assembleia'!D29*C66
B67: Apto 0902-1 | C67: 0.004226 | D67: ='Resumo Assembleia'!D29*C67
B68: Apto 0903-1 | C68: 0.003535 | D68: ='Resumo Assembleia'!D29*C68
B69: Apto 0904-1 | C69: 0.003201 | D69: ='Resumo Assembleia'!D29*C69
B70: Apto 0905-1 | C70: 0.004226 | D70: ='Resumo Assembleia'!D29*C70
B71: Apto 0906-1 | C71: 0.004226 | D71: ='Resumo Assembleia'!D29*C71
B72: Apto 0907-1 | C72: 0.003201 | D72: ='Resumo Assembleia'!D29*C72
B73: Apto 0908-1 | C73: 0.003535 | D73: ='Resumo Assembleia'!D29*C73
B74: Apto 1001-1 | C74: 0.004517 | D74: ='Resumo Assembleia'!D29*C74
B75: Apto 1002-1 | C75: 0.004226 | D75: ='Resumo Assembleia'!D29*C75
B76: Apto 1003-1 | C76: 0.003388 | D76: ='Resumo Assembleia'!D29*C76
B77: Apto 1004-1 | C77: 0.003201 | D77: ='Resumo Assembleia'!D29*C77
B78: Apto 1005-1 | C78: 0.004226 | D78: ='Resumo Assembleia'!D29*C78
B79: Apto 1006-1 | C79: 0.004517 | D79: ='Resumo Assembleia'!D29*C79
B80: Apto 1007-1 | C80: 0.003201 | D80: ='Resumo Assembleia'!D29*C80
B81: Apto 1008-1 | C81: 0.003388 | D81: ='Resumo Assembleia'!D29*C81
B82: Apto 1101-1 | C82: 0.004517 | D82: ='Resumo Assembleia'!D29*C82
B83: Apto 1102-1 | C83: 0.004517 | D83: ='Resumo Assembleia'!D29*C83
B84: Apto 1103-1 | C84: 0.003535 | D84: ='Resumo Assembleia'!D29*C84
B85: Apto 1104-1 | C85: 0.003201 | D85: ='Resumo Assembleia'!D29*C85
B86: Apto 1105-1 | C86: 0.004517 | D86: ='Resumo Assembleia'!D29*C86
B87: Apto 1106-1 | C87: 0.004517 | D87: ='Resumo Assembleia'!D29*C87
B88: Apto 1107-1 | C88: 0.003201 | D88: ='Resumo Assembleia'!D29*C88
B89: Apto 1108-1 | C89: 0.003535 | D89: ='Resumo Assembleia'!D29*C89
B90: Apto 0101-2 | C90: 0.004226 | D90: ='Resumo Assembleia'!D29*C90
B91: Apto 0102-2 | C91: 0.00408 | D91: ='Resumo Assembleia'!D29*C91
B92: Apto 0103-2 | C92: 0.003388 | D92: ='Resumo Assembleia'!D29*C92
B93: Apto 0104-2 | C93: 0.003201 | D93: ='Resumo Assembleia'!D29*C93
B94: Apto 0105-2 | C94: 0.004226 | D94: ='Resumo Assembleia'!D29*C94
B95: Apto 0106-2 | C95: 0.00408 | D95: ='Resumo Assembleia'!D29*C95
B96: Apto 0107-2 | C96: 0.003201 | D96: ='Resumo Assembleia'!D29*C96
B97: Apto 0108-2 | C97: 0.003388 | D97: ='Resumo Assembleia'!D29*C97
B98: Apto 0201-2 | C98: 0.004226 | D98: ='Resumo Assembleia'!D29*C98
B99: Apto 0202-2 | C99: 0.004226 | D99: ='Resumo Assembleia'!D29*C99
B100: Apto 0203-2 | C100: 0.003388 | D100: ='Resumo Assembleia'!D29*C100
...

Sheet Notas (Por Fora)
B2: ITENS POR FORA DO RATEIO
B3: Itens que NÃO entram no cálculo da taxa condominial. Aparecem como nota na apresentação da assembleia, para total transparência.
B5: Item | C5: Categoria de Origem | D5: Total Anual (R$) | E5: Motivo
B6: Empréstimo Energia Solar | C6: Despesas Financeiras | D6: 89430.96 | E6: Financiamento com prazo definido, custeado por arrecadação específica.
B7: Energia | C7: Consumo e Taxas | D7: 28144.74 | E7: Rateado separadamente (medição/cobrança individual).
B8: Telefone | C8: Consumo e Taxas | D8: 3182.24 | E8: Rateado separadamente (medição/cobrança individual).
B9: Telefonia-Internet | C9: Consumo e Taxas | D9: 1299.99 | E9: Rateado separadamente (medição/cobrança individual).
B10: Água-Esgoto | C10: Consumo e Taxas | D10: 369653.27 | E10: Rateado separadamente (medição/cobrança individual).
B11: Materiais Obras-Melhorias | C11: Aquisição de Materiais | D11: 250000 | E11: Obra extraordinária não recorrente (evento único).
B12: TOTAL POR FORA | D12: =SUM(D6:D11)
